{".class":"MypyFile","_fullname":"zict.buffer","future_import_flags":["annotations"],"is_partial_stub_package":false,"is_stub":false,"names":{".class":"SymbolTable","Buffer":{".class":"SymbolTableNode","kind":"Gdef","node":{".class":"TypeInfo","_promote":[],"abstract_attributes":[],"alt_promote":null,"bases":[{".class":"Instance","args":[{".class":"TypeVarType","default":{".class":"AnyType","missing_import_name":null,"source_any":null,"type_of_any":4},"fullname":"zict.common.KT","id":1,"name":"KT","namespace":"zict.buffer.Buffer","upper_bound":"builtins.object","values":[],"variance":0},{".class":"TypeVarType","default":{".class":"AnyType","missing_import_name":null,"source_any":null,"type_of_any":4},"fullname":"zict.common.VT","id":2,"name":"VT","namespace":"zict.buffer.Buffer","upper_bound":"builtins.object","values":[],"variance":0}],"extra_attrs":null,"type_ref":"zict.common.ZictBase"}],"dataclass_transform_spec":null,"declared_metaclass":null,"defn":{".class":"ClassDef","fullname":"zict.buffer.Buffer","name":"Buffer","type_vars":[{".class":"TypeVarType","default":{".class":"AnyType","missing_import_name":null,"source_any":null,"type_of_any":4},"fullname":"zict.common.KT","id":1,"name":"KT","namespace":"zict.buffer.Buffer","upper_bound":"builtins.object","values":[],"variance":0},{".class":"TypeVarType","default":{".class":"AnyType","missing_import_name":null,"source_any":null,"type_of_any":4},"fullname":"zict.common.VT","id":2,"name":"VT","namespace":"zict.buffer.Buffer","upper_bound":"builtins.object","values":[],"variance":0}]},"deletable_attributes":[],"deprecated":null,"flags":[],"fullname":"zict.buffer.Buffer","has_param_spec_type":false,"metaclass_type":"abc.ABCMeta","metadata":{},"module_name":"zict.buffer","mro":["zict.buffer.Buffer","zict.common.ZictBase","typing.MutableMapping","typing.Mapping","typing.Collection","typing.Iterable","typing.Container","builtins.object"],"names":{".class":"SymbolTable","__contains__":{".class":"SymbolTableNode","kind":"Mdef","node":{".class":"FuncDef","abstract_status":0,"arg_kinds":[0,0],"arg_names":[null,null],"dataclass_transform_spec":null,"deprecated":null,"flags":[],"fullname":"zict.buffer.Buffer.__contains__","name":"__contains__","type":{".class":"CallableType","arg_kinds":[0,0],"arg_names":[null,null],"arg_types":[{".class":"Instance","args":[{".class":"TypeVarType","default":{".class":"AnyType","missing_import_name":null,"source_any":null,"type_of_any":4},"fullname":"zict.common.KT","id":1,"name":"KT","namespace":"zict.buffer.Buffer","upper_bound":"builtins.object","values":[],"variance":0},{".class":"TypeVarType","default":{".class":"AnyType","missing_import_name":null,"source_any":null,"type_of_any":4},"fullname":"zict.common.VT","id":2,"name":"VT","namespace":"zict.buffer.Buffer","upper_bound":"builtins.object","values":[],"variance":0}],"extra_attrs":null,"type_ref":"zict.buffer.Buffer"},"builtins.object"],"bound_args":[],"def_extras":{"first_arg":"self"},"fallback":"builtins.function","from_concatenate":false,"implicit":false,"imprecise_arg_kinds":false,"is_ellipsis_args":false,"name":"__contains__ of Buffer","ret_type":"builtins.bool","type_guard":null,"type_is":null,"unpack_kwargs":false,"variables":[]}}},"__delitem__":{".class":"SymbolTableNode","kind":"Mdef","node":{".class":"Decorator","func":{".class":"FuncDef","abstract_status":0,"arg_kinds":[0,0],"arg_names":[null,null],"dataclass_transform_spec":null,"deprecated":null,"flags":["is_decorated"],"fullname":"zict.buffer.Buffer.__delitem__","name":"__delitem__","type":{".class":"CallableType","arg_kinds":[0,0],"arg_names":[null,null],"arg_types":[{".class":"Instance","args":[{".class":"TypeVarType","default":{".class":"AnyType","missing_import_name":null,"source_any":null,"type_of_any":4},"fullname":"zict.common.KT","id":1,"name":"KT","namespace":"zict.buffer.Buffer","upper_bound":"builtins.object","values":[],"variance":0},{".class":"TypeVarType","default":{".class":"AnyType","missing_import_name":null,"source_any":null,"type_of_any":4},"fullname":"zict.common.VT","id":2,"name":"VT","namespace":"zict.buffer.Buffer","upper_bound":"builtins.object","values":[],"variance":0}],"extra_attrs":null,"type_ref":"zict.buffer.Buffer"},{".class":"TypeVarType","default":{".class":"AnyType","missing_import_name":null,"source_any":null,"type_of_any":4},"fullname":"zict.common.KT","id":1,"name":"KT","namespace":"zict.buffer.Buffer","upper_bound":"builtins.object","values":[],"variance":0}],"bound_args":[],"def_extras":{"first_arg":"self"},"fallback":"builtins.function","from_concatenate":false,"implicit":false,"imprecise_arg_kinds":false,"is_ellipsis_args":false,"name":"__delitem__ of Buffer","ret_type":{".class":"NoneType"},"type_guard":null,"type_is":null,"unpack_kwargs":false,"variables":[]}},"is_overload":false,"var":{".class":"Var","flags":["is_initialized_in_class","is_ready","is_inferred"],"fullname":"zict.buffer.Buffer.__delitem__","name":"__delitem__","type":{".class":"CallableType","arg_kinds":[0,0],"arg_names":[null,null],"arg_types":[{".class":"Instance","args":[{".class":"TypeVarType","default":{".class":"AnyType","missing_import_name":null,"source_any":null,"type_of_any":4},"fullname":"zict.common.KT","id":1,"name":"KT","namespace":"zict.buffer.Buffer","upper_bound":"builtins.object","values":[],"variance":0},{".class":"TypeVarType","default":{".class":"AnyType","missing_import_name":null,"source_any":null,"type_of_any":4},"fullname":"zict.common.VT","id":2,"name":"VT","namespace":"zict.buffer.Buffer","upper_bound":"builtins.object","values":[],"variance":0}],"extra_attrs":null,"type_ref":"zict.buffer.Buffer"},{".class":"TypeVarType","default":{".class":"AnyType","missing_import_name":null,"source_any":null,"type_of_any":4},"fullname":"zict.common.KT","id":1,"name":"KT","namespace":"zict.buffer.Buffer","upper_bound":"builtins.object","values":[],"variance":0}],"bound_args":[],"def_extras":{},"fallback":"builtins.function","from_concatenate":false,"implicit":false,"imprecise_arg_kinds":false,"is_ellipsis_args":false,"name":"__delitem__ of Buffer","ret_type":{".class":"NoneType"},"type_guard":null,"type_is":null,"unpack_kwargs":false,"variables":[]}}}},"__getitem__":{".class":"SymbolTableNode","kind":"Mdef","node":{".class":"Decorator","func":{".class":"FuncDef","abstract_status":0,"arg_kinds":[0,0],"arg_names":[null,null],"dataclass_transform_spec":null,"deprecated":null,"flags":["is_decorated"],"fullname":"zict.buffer.Buffer.__getitem__","name":"__getitem__","type":{".class":"CallableType","arg_kinds":[0,0],"arg_names":[null,null],"arg_types":[{".class":"Instance","args":[{".class":"TypeVarType","default":{".class":"AnyType","missing_import_name":null,"source_any":null,"type_of_any":4},"fullname":"zict.common.KT","id":1,"name":"KT","namespace":"zict.buffer.Buffer","upper_bound":"builtins.object","values":[],"variance":0},{".class":"TypeVarType","default":{".class":"AnyType","missing_import_name":null,"source_any":null,"type_of_any":4},"fullname":"zict.common.VT","id":2,"name":"VT","namespace":"zict.buffer.Buffer","upper_bound":"builtins.object","values":[],"variance":0}],"extra_attrs":null,"type_ref":"zict.buffer.Buffer"},{".class":"TypeVarType","default":{".class":"AnyType","missing_import_name":null,"source_any":null,"type_of_any":4},"fullname":"zict.common.KT","id":1,"name":"KT","namespace":"zict.buffer.Buffer","upper_bound":"builtins.object","values":[],"variance":0}],"bound_args":[],"def_extras":{"first_arg":"self"},"fallback":"builtins.function","from_concatenate":false,"implicit":false,"imprecise_arg_kinds":false,"is_ellipsis_args":false,"name":"__getitem__ of Buffer","ret_type":{".class":"TypeVarType","default":{".class":"AnyType","missing_import_name":null,"source_any":null,"type_of_any":4},"fullname":"zict.common.VT","id":2,"name":"VT","namespace":"zict.buffer.Buffer","upper_bound":"builtins.object","values":[],"variance":0},"type_guard":null,"type_is":null,"unpack_kwargs":false,"variables":[]}},"is_overload":false,"var":{".class":"Var","flags":["is_initialized_in_class","is_ready","is_inferred"],"fullname":"zict.buffer.Buffer.__getitem__","name":"__getitem__","type":{".class":"CallableType","arg_kinds":[0,0],"arg_names":[null,null],"arg_types":[{".class":"Instance","args":[{".class":"TypeVarType","default":{".class":"AnyType","missing_import_name":null,"source_any":null,"type_of_any":4},"fullname":"zict.common.KT","id":1,"name":"KT","namespace":"zict.buffer.Buffer","upper_bound":"builtins.object","values":[],"variance":0},{".class":"TypeVarType","default":{".class":"AnyType","missing_import_name":null,"source_any":null,"type_of_any":4},"fullname":"zict.common.VT","id":2,"name":"VT","namespace":"zict.buffer.Buffer","upper_bound":"builtins.object","values":[],"variance":0}],"extra_attrs":null,"type_ref":"zict.buffer.Buffer"},{".class":"TypeVarType","default":{".class":"AnyType","missing_import_name":null,"source_any":null,"type_of_any":4},"fullname":"zict.common.KT","id":1,"name":"KT","namespace":"zict.buffer.Buffer","upper_bound":"builtins.object","values":[],"variance":0}],"bound_args":[],"def_extras":{},"fallback":"builtins.function","from_concatenate":false,"implicit":false,"imprecise_arg_kinds":false,"is_ellipsis_args":false,"name":"__getitem__ of Buffer","ret_type":{".class":"TypeVarType","default":{".class":"AnyType","missing_import_name":null,"source_any":null,"type_of_any":4},"fullname":"zict.common.VT","id":2,"name":"VT","namespace":"zict.buffer.Buffer","upper_bound":"builtins.object","values":[],"variance":0},"type_guard":null,"type_is":null,"unpack_kwargs":false,"variables":[]}}}},"__init__":{".class":"SymbolTableNode","kind":"Mdef","node":{".class":"FuncDef","abstract_status":0,"arg_kinds":[0,0,0,0,1,1,1],"arg_names":["self","fast","slow","n","weight","fast_to_slow_callbacks","slow_to_fast_callbacks"],"dataclass_transform_spec":null,"deprecated":null,"flags":[],"fullname":"zict.buffer.Buffer.__init__","name":"__init__","type":{".class":"CallableType","arg_kinds":[0,0,0,0,1,1,1],"arg_names":["self","fast","slow","n","weight","fast_to_slow_callbacks","slow_to_fast_callbacks"],"arg_types":[{".class":"Instance","args":[{".class":"TypeVarType","default":{".class":"AnyType","missing_import_name":null,"source_any":null,"type_of_any":4},"fullname":"zict.common.KT","id":1,"name":"KT","namespace":"zict.buffer.Buffer","upper_bound":"builtins.object","values":[],"variance":0},{".class":"TypeVarType","default":{".class":"AnyType","missing_import_name":null,"source_any":null,"type_of_any":4},"fullname":"zict.common.VT","id":2,"name":"VT","namespace":"zict.buffer.Buffer","upper_bound":"builtins.object","values":[],"variance":0}],"extra_attrs":null,"type_ref":"zict.buffer.Buffer"},{".class":"Instance","args":[{".class":"TypeVarType","default":{".class":"AnyType","missing_import_name":null,"source_any":null,"type_of_any":4},"fullname":"zict.common.KT","id":1,"name":"KT","namespace":"zict.buffer.Buffer","upper_bound":"builtins.object","values":[],"variance":0},{".class":"TypeVarType","default":{".class":"AnyType","missing_import_name":null,"source_any":null,"type_of_any":4},"fullname":"zict.common.VT","id":2,"name":"VT","namespace":"zict.buffer.Buffer","upper_bound":"builtins.object","values":[],"variance":0}],"extra_attrs":null,"type_ref":"typing.MutableMapping"},{".class":"Instance","args":[{".class":"TypeVarType","default":{".class":"AnyType","missing_import_name":null,"source_any":null,"type_of_any":4},"fullname":"zict.common.KT","id":1,"name":"KT","namespace":"zict.buffer.Buffer","upper_bound":"builtins.object","values":[],"variance":0},{".class":"TypeVarType","default":{".class":"AnyType","missing_import_name":null,"source_any":null,"type_of_any":4},"fullname":"zict.common.VT","id":2,"name":"VT","namespace":"zict.buffer.Buffer","upper_bound":"builtins.object","values":[],"variance":0}],"extra_attrs":null,"type_ref":"typing.MutableMapping"},"builtins.float",{".class":"CallableType","arg_kinds":[0,0],"arg_names":[null,null],"arg_types":[{".class":"TypeVarType","default":{".class":"AnyType","missing_import_name":null,"source_any":null,"type_of_any":4},"fullname":"zict.common.KT","id":1,"name":"KT","namespace":"zict.buffer.Buffer","upper_bound":"builtins.object","values":[],"variance":0},{".class":"TypeVarType","default":{".class":"AnyType","missing_import_name":null,"source_any":null,"type_of_any":4},"fullname":"zict.common.VT","id":2,"name":"VT","namespace":"zict.buffer.Buffer","upper_bound":"builtins.object","values":[],"variance":0}],"bound_args":[],"def_extras":{},"fallback":"builtins.function","from_concatenate":false,"implicit":false,"imprecise_arg_kinds":false,"is_ellipsis_args":false,"name":null,"ret_type":"builtins.float","type_guard":null,"type_is":null,"unpack_kwargs":false,"variables":[]},{".class":"UnionType","items":[{".class":"CallableType","arg_kinds":[0,0],"arg_names":[null,null],"arg_types":[{".class":"TypeVarType","default":{".class":"AnyType","missing_import_name":null,"source_any":null,"type_of_any":4},"fullname":"zict.common.KT","id":1,"name":"KT","namespace":"zict.buffer.Buffer","upper_bound":"builtins.object","values":[],"variance":0},{".class":"TypeVarType","default":{".class":"AnyType","missing_import_name":null,"source_any":null,"type_of_any":4},"fullname":"zict.common.VT","id":2,"name":"VT","namespace":"zict.buffer.Buffer","upper_bound":"builtins.object","values":[],"variance":0}],"bound_args":[],"def_extras":{},"fallback":"builtins.function","from_concatenate":false,"implicit":false,"imprecise_arg_kinds":false,"is_ellipsis_args":false,"name":null,"ret_type":{".class":"NoneType"},"type_guard":null,"type_is":null,"unpack_kwargs":false,"variables":[]},{".class":"Instance","args":[{".class":"CallableType","arg_kinds":[0,0],"arg_names":[null,null],"arg_types":[{".class":"TypeVarType","default":{".class":"AnyType","missing_import_name":null,"source_any":null,"type_of_any":4},"fullname":"zict.common.KT","id":1,"name":"KT","namespace":"zict.buffer.Buffer","upper_bound":"builtins.object","values":[],"variance":0},{".class":"TypeVarType","default":{".class":"AnyType","missing_import_name":null,"source_any":null,"type_of_any":4},"fullname":"zict.common.VT","id":2,"name":"VT","namespace":"zict.buffer.Buffer","upper_bound":"builtins.object","values":[],"variance":0}],"bound_args":[],"def_extras":{},"fallback":"builtins.function","from_concatenate":false,"implicit":false,"imprecise_arg_kinds":false,"is_ellipsis_args":false,"name":null,"ret_type":{".class":"NoneType"},"type_guard":null,"type_is":null,"unpack_kwargs":false,"variables":[]}],"extra_attrs":null,"type_ref":"builtins.list"},{".class":"NoneType"}],"uses_pep604_syntax":true},{".class":"UnionType","items":[{".class":"CallableType","arg_kinds":[0,0],"arg_names":[null,null],"arg_types":[{".class":"TypeVarType","default":{".class":"AnyType","missing_import_name":null,"source_any":null,"type_of_any":4},"fullname":"zict.common.KT","id":1,"name":"KT","namespace":"zict.buffer.Buffer","upper_bound":"builtins.object","values":[],"variance":0},{".class":"TypeVarType","default":{".class":"AnyType","missing_import_name":null,"source_any":null,"type_of_any":4},"fullname":"zict.common.VT","id":2,"name":"VT","namespace":"zict.buffer.Buffer","upper_bound":"builtins.object","values":[],"variance":0}],"bound_args":[],"def_extras":{},"fallback":"builtins.function","from_concatenate":false,"implicit":false,"imprecise_arg_kinds":false,"is_ellipsis_args":false,"name":null,"ret_type":{".class":"NoneType"},"type_guard":null,"type_is":null,"unpack_kwargs":false,"variables":[]},{".class":"Instance","args":[{".class":"CallableType","arg_kinds":[0,0],"arg_names":[null,null],"arg_types":[{".class":"TypeVarType","default":{".class":"AnyType","missing_import_name":null,"source_any":null,"type_of_any":4},"fullname":"zict.common.KT","id":1,"name":"KT","namespace":"zict.buffer.Buffer","upper_bound":"builtins.object","values":[],"variance":0},{".class":"TypeVarType","default":{".class":"AnyType","missing_import_name":null,"source_any":null,"type_of_any":4},"fullname":"zict.common.VT","id":2,"name":"VT","namespace":"zict.buffer.Buffer","upper_bound":"builtins.object","values":[],"variance":0}],"bound_args":[],"def_extras":{},"fallback":"builtins.function","from_concatenate":false,"implicit":false,"imprecise_arg_kinds":false,"is_ellipsis_args":false,"name":null,"ret_type":{".class":"NoneType"},"type_guard":null,"type_is":null,"unpack_kwargs":false,"variables":[]}],"extra_attrs":null,"type_ref":"builtins.list"},{".class":"NoneType"}],"uses_pep604_syntax":true}],"bound_args":[],"def_extras":{"first_arg":"self"},"fallback":"builtins.function","from_concatenate":false,"implicit":false,"imprecise_arg_kinds":false,"is_ellipsis_args":false,"name":"__init__ of Buffer","ret_type":{".class":"NoneType"},"type_guard":null,"type_is":null,"unpack_kwargs":false,"variables":[]}}},"__iter__":{".class":"SymbolTableNode","kind":"Mdef","node":{".class":"FuncDef","abstract_status":0,"arg_kinds":[0],"arg_names":[null],"dataclass_transform_spec":null,"deprecated":null,"flags":[],"fullname":"zict.buffer.Buffer.__iter__","name":"__iter__","type":{".class":"CallableType","arg_kinds":[0],"arg_names":[null],"arg_types":[{".class":"Instance","args":[{".class":"TypeVarType","default":{".class":"AnyType","missing_import_name":null,"source_any":null,"type_of_any":4},"fullname":"zict.common.KT","id":1,"name":"KT","namespace":"zict.buffer.Buffer","upper_bound":"builtins.object","values":[],"variance":0},{".class":"TypeVarType","default":{".class":"AnyType","missing_import_name":null,"source_any":null,"type_of_any":4},"fullname":"zict.common.VT","id":2,"name":"VT","namespace":"zict.buffer.Buffer","upper_bound":"builtins.object","values":[],"variance":0}],"extra_attrs":null,"type_ref":"zict.buffer.Buffer"}],"bound_args":[],"def_extras":{"first_arg":"self"},"fallback":"builtins.function","from_concatenate":false,"implicit":false,"imprecise_arg_kinds":false,"is_ellipsis_args":false,"name":"__iter__ of Buffer","ret_type":{".class":"Instance","args":[{".class":"TypeVarType","default":{".class":"AnyType","missing_import_name":null,"source_any":null,"type_of_any":4},"fullname":"zict.common.KT","id":1,"name":"KT","namespace":"zict.buffer.Buffer","upper_bound":"builtins.object","values":[],"variance":0}],"extra_attrs":null,"type_ref":"typing.Iterator"},"type_guard":null,"type_is":null,"unpack_kwargs":false,"variables":[]}}},"__len__":{".class":"SymbolTableNode","kind":"Mdef","node":{".class":"FuncDef","abstract_status":0,"arg_kinds":[0],"arg_names":[null],"dataclass_transform_spec":null,"deprecated":null,"flags":[],"fullname":"zict.buffer.Buffer.__len__","name":"__len__","type":{".class":"CallableType","arg_kinds":[0],"arg_names":[null],"arg_types":[{".class":"Instance","args":[{".class":"TypeVarType","default":{".class":"AnyType","missing_import_name":null,"source_any":null,"type_of_any":4},"fullname":"zict.common.KT","id":1,"name":"KT","namespace":"zict.buffer.Buffer","upper_bound":"builtins.object","values":[],"variance":0},{".class":"TypeVarType","default":{".class":"AnyType","missing_import_name":null,"source_any":null,"type_of_any":4},"fullname":"zict.common.VT","id":2,"name":"VT","namespace":"zict.buffer.Buffer","upper_bound":"builtins.object","values":[],"variance":0}],"extra_attrs":null,"type_ref":"zict.buffer.Buffer"}],"bound_args":[],"def_extras":{"first_arg":"self"},"fallback":"builtins.function","from_concatenate":false,"implicit":false,"imprecise_arg_kinds":false,"is_ellipsis_args":false,"name":"__len__ of Buffer","ret_type":"builtins.int","type_guard":null,"type_is":null,"unpack_kwargs":false,"variables":[]}}},"__repr__":{".class":"SymbolTableNode","kind":"Mdef","node":{".class":"Var","flags":["is_initialized_in_class","is_inferred","has_explicit_value"],"fullname":"zict.buffer.Buffer.__repr__","name":"__repr__","type":{".class":"CallableType","arg_kinds":[0],"arg_names":[null],"arg_types":[{".class":"Instance","args":[{".class":"TypeVarType","default":{".class":"AnyType","missing_import_name":null,"source_any":null,"type_of_any":4},"fullname":"zict.common.KT","id":1,"name":"KT","namespace":"zict.buffer.Buffer","upper_bound":"builtins.object","values":[],"variance":0},{".class":"TypeVarType","default":{".class":"AnyType","missing_import_name":null,"source_any":null,"type_of_any":4},"fullname":"zict.common.VT","id":2,"name":"VT","namespace":"zict.buffer.Buffer","upper_bound":"builtins.object","values":[],"variance":0}],"extra_attrs":null,"type_ref":"zict.buffer.Buffer"}],"bound_args":[],"def_extras":{"first_arg":"self"},"fallback":"builtins.function","from_concatenate":false,"implicit":false,"imprecise_arg_kinds":false,"is_ellipsis_args":false,"name":null,"ret_type":"builtins.str","type_guard":null,"type_is":null,"unpack_kwargs":false,"variables":[]}}},"__setitem__":{".class":"SymbolTableNode","kind":"Mdef","node":{".class":"FuncDef","abstract_status":0,"arg_kinds":[0,0,0],"arg_names":[null,null,null],"dataclass_transform_spec":null,"deprecated":null,"flags":[],"fullname":"zict.buffer.Buffer.__setitem__","name":"__setitem__","type":{".class":"CallableType","arg_kinds":[0,0,0],"arg_names":[null,null,null],"arg_types":[{".class":"Instance","args":[{".class":"TypeVarType","default":{".class":"AnyType","missing_import_name":null,"source_any":null,"type_of_any":4},"fullname":"zict.common.KT","id":1,"name":"KT","namespace":"zict.buffer.Buffer","upper_bound":"builtins.object","values":[],"variance":0},{".class":"TypeVarType","default":{".class":"AnyType","missing_import_name":null,"source_any":null,"type_of_any":4},"fullname":"zict.common.VT","id":2,"name":"VT","namespace":"zict.buffer.Buffer","upper_bound":"builtins.object","values":[],"variance":0}],"extra_attrs":null,"type_ref":"zict.buffer.Buffer"},{".class":"TypeVarType","default":{".class":"AnyType","missing_import_name":null,"source_any":null,"type_of_any":4},"fullname":"zict.common.KT","id":1,"name":"KT","namespace":"zict.buffer.Buffer","upper_bound":"builtins.object","values":[],"variance":0},{".class":"TypeVarType","default":{".class":"AnyType","missing_import_name":null,"source_any":null,"type_of_any":4},"fullname":"zict.common.VT","id":2,"name":"VT","namespace":"zict.buffer.Buffer","upper_bound":"builtins.object","values":[],"variance":0}],"bound_args":[],"def_extras":{"first_arg":"self"},"fallback":"builtins.function","from_concatenate":false,"implicit":false,"imprecise_arg_kinds":false,"is_ellipsis_args":false,"name":"__setitem__ of Buffer","ret_type":{".class":"NoneType"},"type_guard":null,"type_is":null,"unpack_kwargs":false,"variables":[]}}},"__str__":{".class":"SymbolTableNode","kind":"Mdef","node":{".class":"FuncDef","abstract_status":0,"arg_kinds":[0],"arg_names":[null],"dataclass_transform_spec":null,"deprecated":null,"flags":[],"fullname":"zict.buffer.Buffer.__str__","name":"__str__","type":{".class":"CallableType","arg_kinds":[0],"arg_names":[null],"arg_types":[{".class":"Instance","args":[{".class":"TypeVarType","default":{".class":"AnyType","missing_import_name":null,"source_any":null,"type_of_any":4},"fullname":"zict.common.KT","id":1,"name":"KT","namespace":"zict.buffer.Buffer","upper_bound":"builtins.object","values":[],"variance":0},{".class":"TypeVarType","default":{".class":"AnyType","missing_import_name":null,"source_any":null,"type_of_any":4},"fullname":"zict.common.VT","id":2,"name":"VT","namespace":"zict.buffer.Buffer","upper_bound":"builtins.object","values":[],"variance":0}],"extra_attrs":null,"type_ref":"zict.buffer.Buffer"}],"bound_args":[],"def_extras":{"first_arg":"self"},"fallback":"builtins.function","from_concatenate":false,"implicit":false,"imprecise_arg_kinds":false,"is_ellipsis_args":false,"name":"__str__ of Buffer","ret_type":"builtins.str","type_guard":null,"type_is":null,"unpack_kwargs":false,"variables":[]}}},"_cancel_evict":{".class":"SymbolTableNode","kind":"Mdef","node":{".class":"Decorator","func":{".class":"FuncDef","abstract_status":0,"arg_kinds":[0,0,0],"arg_names":["self","key","value"],"dataclass_transform_spec":null,"deprecated":null,"flags":["is_decorated"],"fullname":"zict.buffer.Buffer._cancel_evict","name":"_cancel_evict","type":{".class":"CallableType","arg_kinds":[0,0,0],"arg_names":["self","key","value"],"arg_types":[{".class":"Instance","args":[{".class":"TypeVarType","default":{".class":"AnyType","missing_import_name":null,"source_any":null,"type_of_any":4},"fullname":"zict.common.KT","id":1,"name":"KT","namespace":"zict.buffer.Buffer","upper_bound":"builtins.object","values":[],"variance":0},{".class":"TypeVarType","default":{".class":"AnyType","missing_import_name":null,"source_any":null,"type_of_any":4},"fullname":"zict.common.VT","id":2,"name":"VT","namespace":"zict.buffer.Buffer","upper_bound":"builtins.object","values":[],"variance":0}],"extra_attrs":null,"type_ref":"zict.buffer.Buffer"},{".class":"TypeVarType","default":{".class":"AnyType","missing_import_name":null,"source_any":null,"type_of_any":4},"fullname":"zict.common.KT","id":1,"name":"KT","namespace":"zict.buffer.Buffer","upper_bound":"builtins.object","values":[],"variance":0},{".class":"TypeVarType","default":{".class":"AnyType","missing_import_name":null,"source_any":null,"type_of_any":4},"fullname":"zict.common.VT","id":2,"name":"VT","namespace":"zict.buffer.Buffer","upper_bound":"builtins.object","values":[],"variance":0}],"bound_args":[],"def_extras":{"first_arg":"self"},"fallback":"builtins.function","from_concatenate":false,"implicit":false,"imprecise_arg_kinds":false,"is_ellipsis_args":false,"name":"_cancel_evict of Buffer","ret_type":{".class":"NoneType"},"type_guard":null,"type_is":null,"unpack_kwargs":false,"variables":[]}},"is_overload":false,"var":{".class":"Var","flags":["is_initialized_in_class","is_ready","is_inferred"],"fullname":"zict.buffer.Buffer._cancel_evict","name":"_cancel_evict","type":{".class":"CallableType","arg_kinds":[0,0,0],"arg_names":["self","key","value"],"arg_types":[{".class":"Instance","args":[{".class":"TypeVarType","default":{".class":"AnyType","missing_import_name":null,"source_any":null,"type_of_any":4},"fullname":"zict.common.KT","id":1,"name":"KT","namespace":"zict.buffer.Buffer","upper_bound":"builtins.object","values":[],"variance":0},{".class":"TypeVarType","default":{".class":"AnyType","missing_import_name":null,"source_any":null,"type_of_any":4},"fullname":"zict.common.VT","id":2,"name":"VT","namespace":"zict.buffer.Buffer","upper_bound":"builtins.object","values":[],"variance":0}],"extra_attrs":null,"type_ref":"zict.buffer.Buffer"},{".class":"TypeVarType","default":{".class":"AnyType","missing_import_name":null,"source_any":null,"type_of_any":4},"fullname":"zict.common.KT","id":1,"name":"KT","namespace":"zict.buffer.Buffer","upper_bound":"builtins.object","values":[],"variance":0},{".class":"TypeVarType","default":{".class":"AnyType","missing_import_name":null,"source_any":null,"type_of_any":4},"fullname":"zict.common.VT","id":2,"name":"VT","namespace":"zict.buffer.Buffer","upper_bound":"builtins.object","values":[],"variance":0}],"bound_args":[],"def_extras":{},"fallback":"builtins.function","from_concatenate":false,"implicit":false,"imprecise_arg_kinds":false,"is_ellipsis_args":false,"name":"_cancel_evict of Buffer","ret_type":{".class":"NoneType"},"type_guard":null,"type_is":null,"unpack_kwargs":false,"variables":[]}}}},"_cancel_restore":{".class":"SymbolTableNode","kind":"Mdef","node":{".class":"Var","flags":["is_initialized_in_class","is_ready"],"fullname":"zict.buffer.Buffer._cancel_restore","name":"_cancel_restore","type":{".class":"Instance","args":[{".class":"TypeVarType","default":{".class":"AnyType","missing_import_name":null,"source_any":null,"type_of_any":4},"fullname":"zict.common.KT","id":1,"name":"KT","namespace":"zict.buffer.Buffer","upper_bound":"builtins.object","values":[],"variance":0},"builtins.bool"],"extra_attrs":null,"type_ref":"builtins.dict"}}},"close":{".class":"SymbolTableNode","kind":"Mdef","node":{".class":"FuncDef","abstract_status":0,"arg_kinds":[0],"arg_names":["self"],"dataclass_transform_spec":null,"deprecated":null,"flags":[],"fullname":"zict.buffer.Buffer.close","name":"close","type":{".class":"CallableType","arg_kinds":[0],"arg_names":["self"],"arg_types":[{".class":"Instance","args":[{".class":"TypeVarType","default":{".class":"AnyType","missing_import_name":null,"source_any":null,"type_of_any":4},"fullname":"zict.common.KT","id":1,"name":"KT","namespace":"zict.buffer.Buffer","upper_bound":"builtins.object","values":[],"variance":0},{".class":"TypeVarType","default":{".class":"AnyType","missing_import_name":null,"source_any":null,"type_of_any":4},"fullname":"zict.common.VT","id":2,"name":"VT","namespace":"zict.buffer.Buffer","upper_bound":"builtins.object","values":[],"variance":0}],"extra_attrs":null,"type_ref":"zict.buffer.Buffer"}],"bound_args":[],"def_extras":{"first_arg":"self"},"fallback":"builtins.function","from_concatenate":false,"implicit":false,"imprecise_arg_kinds":false,"is_ellipsis_args":false,"name":"close of Buffer","ret_type":{".class":"NoneType"},"type_guard":null,"type_is":null,"unpack_kwargs":false,"variables":[]}}},"evict_until_below_target":{".class":"SymbolTableNode","kind":"Mdef","node":{".class":"FuncDef","abstract_status":0,"arg_kinds":[0,1],"arg_names":["self","n"],"dataclass_transform_spec":null,"deprecated":null,"flags":[],"fullname":"zict.buffer.Buffer.evict_until_below_target","name":"evict_until_below_target","type":{".class":"CallableType","arg_kinds":[0,1],"arg_names":["self","n"],"arg_types":[{".class":"Instance","args":[{".class":"TypeVarType","default":{".class":"AnyType","missing_import_name":null,"source_any":null,"type_of_any":4},"fullname":"zict.common.KT","id":1,"name":"KT","namespace":"zict.buffer.Buffer","upper_bound":"builtins.object","values":[],"variance":0},{".class":"TypeVarType","default":{".class":"AnyType","missing_import_name":null,"source_any":null,"type_of_any":4},"fullname":"zict.common.VT","id":2,"name":"VT","namespace":"zict.buffer.Buffer","upper_bound":"builtins.object","values":[],"variance":0}],"extra_attrs":null,"type_ref":"zict.buffer.Buffer"},{".class":"UnionType","items":["builtins.float",{".class":"NoneType"}],"uses_pep604_syntax":true}],"bound_args":[],"def_extras":{"first_arg":"self"},"fallback":"builtins.function","from_concatenate":false,"implicit":false,"imprecise_arg_kinds":false,"is_ellipsis_args":false,"name":"evict_until_below_target of Buffer","ret_type":{".class":"NoneType"},"type_guard":null,"type_is":null,"unpack_kwargs":false,"variables":[]}}},"fast":{".class":"SymbolTableNode","kind":"Mdef","node":{".class":"Var","flags":["is_initialized_in_class","is_ready"],"fullname":"zict.buffer.Buffer.fast","name":"fast","type":{".class":"Instance","args":[{".class":"TypeVarType","default":{".class":"AnyType","missing_import_name":null,"source_any":null,"type_of_any":4},"fullname":"zict.common.KT","id":1,"name":"KT","namespace":"zict.buffer.Buffer","upper_bound":"builtins.object","values":[],"variance":0},{".class":"TypeVarType","default":{".class":"AnyType","missing_import_name":null,"source_any":null,"type_of_any":4},"fullname":"zict.common.VT","id":2,"name":"VT","namespace":"zict.buffer.Buffer","upper_bound":"builtins.object","values":[],"variance":0}],"extra_attrs":null,"type_ref":"zict.lru.LRU"}}},"fast_to_slow":{".class":"SymbolTableNode","kind":"Mdef","node":{".class":"FuncDef","abstract_status":0,"arg_kinds":[0,0,0],"arg_names":["self","key","value"],"dataclass_transform_spec":null,"deprecated":null,"flags":[],"fullname":"zict.buffer.Buffer.fast_to_slow","name":"fast_to_slow","type":{".class":"CallableType","arg_kinds":[0,0,0],"arg_names":["self","key","value"],"arg_types":[{".class":"Instance","args":[{".class":"TypeVarType","default":{".class":"AnyType","missing_import_name":null,"source_any":null,"type_of_any":4},"fullname":"zict.common.KT","id":1,"name":"KT","namespace":"zict.buffer.Buffer","upper_bound":"builtins.object","values":[],"variance":0},{".class":"TypeVarType","default":{".class":"AnyType","missing_import_name":null,"source_any":null,"type_of_any":4},"fullname":"zict.common.VT","id":2,"name":"VT","namespace":"zict.buffer.Buffer","upper_bound":"builtins.object","values":[],"variance":0}],"extra_attrs":null,"type_ref":"zict.buffer.Buffer"},{".class":"TypeVarType","default":{".class":"AnyType","missing_import_name":null,"source_any":null,"type_of_any":4},"fullname":"zict.common.KT","id":1,"name":"KT","namespace":"zict.buffer.Buffer","upper_bound":"builtins.object","values":[],"variance":0},{".class":"TypeVarType","default":{".class":"AnyType","missing_import_name":null,"source_any":null,"type_of_any":4},"fullname":"zict.common.VT","id":2,"name":"VT","namespace":"zict.buffer.Buffer","upper_bound":"builtins.object","values":[],"variance":0}],"bound_args":[],"def_extras":{"first_arg":"self"},"fallback":"builtins.function","from_concatenate":false,"implicit":false,"imprecise_arg_kinds":false,"is_ellipsis_args":false,"name":"fast_to_slow of Buffer","ret_type":{".class":"NoneType"},"type_guard":null,"type_is":null,"unpack_kwargs":false,"variables":[]}}},"fast_to_slow_callbacks":{".class":"SymbolTableNode","kind":"Mdef","node":{".class":"Var","flags":["is_initialized_in_class","is_ready"],"fullname":"zict.buffer.Buffer.fast_to_slow_callbacks","name":"fast_to_slow_callbacks","type":{".class":"Instance","args":[{".class":"CallableType","arg_kinds":[0,0],"arg_names":[null,null],"arg_types":[{".class":"TypeVarType","default":{".class":"AnyType","missing_import_name":null,"source_any":null,"type_of_any":4},"fullname":"zict.common.KT","id":1,"name":"KT","namespace":"zict.buffer.Buffer","upper_bound":"builtins.object","values":[],"variance":0},{".class":"TypeVarType","default":{".class":"AnyType","missing_import_name":null,"source_any":null,"type_of_any":4},"fullname":"zict.common.VT","id":2,"name":"VT","namespace":"zict.buffer.Buffer","upper_bound":"builtins.object","values":[],"variance":0}],"bound_args":[],"def_extras":{},"fallback":"builtins.function","from_concatenate":false,"implicit":false,"imprecise_arg_kinds":false,"is_ellipsis_args":false,"name":null,"ret_type":{".class":"NoneType"},"type_guard":null,"type_is":null,"unpack_kwargs":false,"variables":[]}],"extra_attrs":null,"type_ref":"builtins.list"}}},"flush":{".class":"SymbolTableNode","kind":"Mdef","node":{".class":"FuncDef","abstract_status":0,"arg_kinds":[0],"arg_names":["self"],"dataclass_transform_spec":null,"deprecated":null,"flags":[],"fullname":"zict.buffer.Buffer.flush","name":"flush","type":{".class":"CallableType","arg_kinds":[0],"arg_names":["self"],"arg_types":[{".class":"Instance","args":[{".class":"TypeVarType","default":{".class":"AnyType","missing_import_name":null,"source_any":null,"type_of_any":4},"fullname":"zict.common.KT","id":1,"name":"KT","namespace":"zict.buffer.Buffer","upper_bound":"builtins.object","values":[],"variance":0},{".class":"TypeVarType","default":{".class":"AnyType","missing_import_name":null,"source_any":null,"type_of_any":4},"fullname":"zict.common.VT","id":2,"name":"VT","namespace":"zict.buffer.Buffer","upper_bound":"builtins.object","values":[],"variance":0}],"extra_attrs":null,"type_ref":"zict.buffer.Buffer"}],"bound_args":[],"def_extras":{"first_arg":"self"},"fallback":"builtins.function","from_concatenate":false,"implicit":false,"imprecise_arg_kinds":false,"is_ellipsis_args":false,"name":"flush of Buffer","ret_type":{".class":"NoneType"},"type_guard":null,"type_is":null,"unpack_kwargs":false,"variables":[]}}},"items":{".class":"SymbolTableNode","kind":"Mdef","node":{".class":"FuncDef","abstract_status":0,"arg_kinds":[0],"arg_names":["self"],"dataclass_transform_spec":null,"deprecated":null,"flags":[],"fullname":"zict.buffer.Buffer.items","name":"items","type":{".class":"CallableType","arg_kinds":[0],"arg_names":["self"],"arg_types":[{".class":"Instance","args":[{".class":"TypeVarType","default":{".class":"AnyType","missing_import_name":null,"source_any":null,"type_of_any":4},"fullname":"zict.common.KT","id":1,"name":"KT","namespace":"zict.buffer.Buffer","upper_bound":"builtins.object","values":[],"variance":0},{".class":"TypeVarType","default":{".class":"AnyType","missing_import_name":null,"source_any":null,"type_of_any":4},"fullname":"zict.common.VT","id":2,"name":"VT","namespace":"zict.buffer.Buffer","upper_bound":"builtins.object","values":[],"variance":0}],"extra_attrs":null,"type_ref":"zict.buffer.Buffer"}],"bound_args":[],"def_extras":{"first_arg":"self"},"fallback":"builtins.function","from_concatenate":false,"implicit":false,"imprecise_arg_kinds":false,"is_ellipsis_args":false,"name":"items of Buffer","ret_type":{".class":"Instance","args":[{".class":"TypeVarType","default":{".class":"AnyType","missing_import_name":null,"source_any":null,"type_of_any":4},"fullname":"zict.common.KT","id":1,"name":"KT","namespace":"zict.buffer.Buffer","upper_bound":"builtins.object","values":[],"variance":0},{".class":"TypeVarType","default":{".class":"AnyType","missing_import_name":null,"source_any":null,"type_of_any":4},"fullname":"zict.common.VT","id":2,"name":"VT","namespace":"zict.buffer.Buffer","upper_bound":"builtins.object","values":[],"variance":0}],"extra_attrs":null,"type_ref":"typing.ItemsView"},"type_guard":null,"type_is":null,"unpack_kwargs":false,"variables":[]}}},"n":{".class":"SymbolTableNode","kind":"Mdef","node":{".class":"OverloadedFuncDef","deprecated":null,"flags":["is_property"],"fullname":"zict.buffer.Buffer.n","impl":null,"items":[{".class":"Decorator","func":{".class":"FuncDef","abstract_status":0,"arg_kinds":[0],"arg_names":["self"],"dataclass_transform_spec":null,"deprecated":null,"flags":["is_property","is_overload","is_decorated"],"fullname":"zict.buffer.Buffer.n","name":"n","type":{".class":"CallableType","arg_kinds":[0],"arg_names":["self"],"arg_types":[{".class":"Instance","args":[{".class":"TypeVarType","default":{".class":"AnyType","missing_import_name":null,"source_any":null,"type_of_any":4},"fullname":"zict.common.KT","id":1,"name":"KT","namespace":"zict.buffer.Buffer","upper_bound":"builtins.object","values":[],"variance":0},{".class":"TypeVarType","default":{".class":"AnyType","missing_import_name":null,"source_any":null,"type_of_any":4},"fullname":"zict.common.VT","id":2,"name":"VT","namespace":"zict.buffer.Buffer","upper_bound":"builtins.object","values":[],"variance":0}],"extra_attrs":null,"type_ref":"zict.buffer.Buffer"}],"bound_args":[],"def_extras":{"first_arg":"self"},"fallback":"builtins.function","from_concatenate":false,"implicit":false,"imprecise_arg_kinds":false,"is_ellipsis_args":false,"name":"n of Buffer","ret_type":"builtins.float","type_guard":null,"type_is":null,"unpack_kwargs":false,"variables":[]}},"is_overload":true,"var":{".class":"Var","flags":["is_initialized_in_class","is_property","is_settable_property","is_ready","is_inferred"],"fullname":"zict.buffer.Buffer.n","name":"n","type":{".class":"CallableType","arg_kinds":[0],"arg_names":["self"],"arg_types":[{".class":"Instance","args":[{".class":"TypeVarType","default":{".class":"AnyType","missing_import_name":null,"source_any":null,"type_of_any":4},"fullname":"zict.common.KT","id":1,"name":"KT","namespace":"zict.buffer.Buffer","upper_bound":"builtins.object","values":[],"variance":0},{".class":"TypeVarType","default":{".class":"AnyType","missing_import_name":null,"source_any":null,"type_of_any":4},"fullname":"zict.common.VT","id":2,"name":"VT","namespace":"zict.buffer.Buffer","upper_bound":"builtins.object","values":[],"variance":0}],"extra_attrs":null,"type_ref":"zict.buffer.Buffer"}],"bound_args":[],"def_extras":{"first_arg":"self"},"fallback":"builtins.function","from_concatenate":false,"implicit":false,"imprecise_arg_kinds":false,"is_ellipsis_args":false,"name":"n of Buffer","ret_type":"builtins.float","type_guard":null,"type_is":null,"unpack_kwargs":false,"variables":[]}}},{".class":"Decorator","func":{".class":"FuncDef","abstract_status":0,"arg_kinds":[0,0],"arg_names":["self","value"],"dataclass_transform_spec":null,"deprecated":null,"flags":["is_decorated"],"fullname":"zict.buffer.Buffer.n","name":"n","type":{".class":"CallableType","arg_kinds":[0,0],"arg_names":["self","value"],"arg_types":[{".class":"Instance","args":[{".class":"TypeVarType","default":{".class":"AnyType","missing_import_name":null,"source_any":null,"type_of_any":4},"fullname":"zict.common.KT","id":1,"name":"KT","namespace":"zict.buffer.Buffer","upper_bound":"builtins.object","values":[],"variance":0},{".class":"TypeVarType","default":{".class":"AnyType","missing_import_name":null,"source_any":null,"type_of_any":4},"fullname":"zict.common.VT","id":2,"name":"VT","namespace":"zict.buffer.Buffer","upper_bound":"builtins.object","values":[],"variance":0}],"extra_attrs":null,"type_ref":"zict.buffer.Buffer"},"builtins.float"],"bound_args":[],"def_extras":{"first_arg":"self"},"fallback":"builtins.function","from_concatenate":false,"implicit":false,"imprecise_arg_kinds":false,"is_ellipsis_args":false,"name":"n of Buffer","ret_type":{".class":"NoneType"},"type_guard":null,"type_is":null,"unpack_kwargs":false,"variables":[]}},"is_overload":false,"var":{".class":"Var","flags":["is_inferred"],"fullname":"","name":"n","type":null}}],"type":{".class":"Overloaded","items":[{".class":"CallableType","arg_kinds":[0],"arg_names":["self"],"arg_types":[{".class":"Instance","args":[{".class":"TypeVarType","default":{".class":"AnyType","missing_import_name":null,"source_any":null,"type_of_any":4},"fullname":"zict.common.KT","id":1,"name":"KT","namespace":"zict.buffer.Buffer","upper_bound":"builtins.object","values":[],"variance":0},{".class":"TypeVarType","default":{".class":"AnyType","missing_import_name":null,"source_any":null,"type_of_any":4},"fullname":"zict.common.VT","id":2,"name":"VT","namespace":"zict.buffer.Buffer","upper_bound":"builtins.object","values":[],"variance":0}],"extra_attrs":null,"type_ref":"zict.buffer.Buffer"}],"bound_args":[],"def_extras":{"first_arg":"self"},"fallback":"builtins.function","from_concatenate":false,"implicit":false,"imprecise_arg_kinds":false,"is_ellipsis_args":false,"name":"n of Buffer","ret_type":"builtins.float","type_guard":null,"type_is":null,"unpack_kwargs":false,"variables":[]}]}}},"offset":{".class":"SymbolTableNode","kind":"Mdef","node":{".class":"OverloadedFuncDef","deprecated":null,"flags":["is_property"],"fullname":"zict.buffer.Buffer.offset","impl":null,"items":[{".class":"Decorator","func":{".class":"FuncDef","abstract_status":0,"arg_kinds":[0],"arg_names":["self"],"dataclass_transform_spec":null,"deprecated":null,"flags":["is_property","is_overload","is_decorated"],"fullname":"zict.buffer.Buffer.offset","name":"offset","type":{".class":"CallableType","arg_kinds":[0],"arg_names":["self"],"arg_types":[{".class":"Instance","args":[{".class":"TypeVarType","default":{".class":"AnyType","missing_import_name":null,"source_any":null,"type_of_any":4},"fullname":"zict.common.KT","id":1,"name":"KT","namespace":"zict.buffer.Buffer","upper_bound":"builtins.object","values":[],"variance":0},{".class":"TypeVarType","default":{".class":"AnyType","missing_import_name":null,"source_any":null,"type_of_any":4},"fullname":"zict.common.VT","id":2,"name":"VT","namespace":"zict.buffer.Buffer","upper_bound":"builtins.object","values":[],"variance":0}],"extra_attrs":null,"type_ref":"zict.buffer.Buffer"}],"bound_args":[],"def_extras":{"first_arg":"self"},"fallback":"builtins.function","from_concatenate":false,"implicit":false,"imprecise_arg_kinds":false,"is_ellipsis_args":false,"name":"offset of Buffer","ret_type":"builtins.float","type_guard":null,"type_is":null,"unpack_kwargs":false,"variables":[]}},"is_overload":true,"var":{".class":"Var","flags":["is_initialized_in_class","is_property","is_settable_property","is_ready","is_inferred"],"fullname":"zict.buffer.Buffer.offset","name":"offset","type":{".class":"CallableType","arg_kinds":[0],"arg_names":["self"],"arg_types":[{".class":"Instance","args":[{".class":"TypeVarType","default":{".class":"AnyType","missing_import_name":null,"source_any":null,"type_of_any":4},"fullname":"zict.common.KT","id":1,"name":"KT","namespace":"zict.buffer.Buffer","upper_bound":"builtins.object","values":[],"variance":0},{".class":"TypeVarType","default":{".class":"AnyType","missing_import_name":null,"source_any":null,"type_of_any":4},"fullname":"zict.common.VT","id":2,"name":"VT","namespace":"zict.buffer.Buffer","upper_bound":"builtins.object","values":[],"variance":0}],"extra_attrs":null,"type_ref":"zict.buffer.Buffer"}],"bound_args":[],"def_extras":{"first_arg":"self"},"fallback":"builtins.function","from_concatenate":false,"implicit":false,"imprecise_arg_kinds":false,"is_ellipsis_args":false,"name":"offset of Buffer","ret_type":"builtins.float","type_guard":null,"type_is":null,"unpack_kwargs":false,"variables":[]}}},{".class":"Decorator","func":{".class":"FuncDef","abstract_status":0,"arg_kinds":[0,0],"arg_names":["self","value"],"dataclass_transform_spec":null,"deprecated":null,"flags":["is_decorated"],"fullname":"zict.buffer.Buffer.offset","name":"offset","type":{".class":"CallableType","arg_kinds":[0,0],"arg_names":["self","value"],"arg_types":[{".class":"Instance","args":[{".class":"TypeVarType","default":{".class":"AnyType","missing_import_name":null,"source_any":null,"type_of_any":4},"fullname":"zict.common.KT","id":1,"name":"KT","namespace":"zict.buffer.Buffer","upper_bound":"builtins.object","values":[],"variance":0},{".class":"TypeVarType","default":{".class":"AnyType","missing_import_name":null,"source_any":null,"type_of_any":4},"fullname":"zict.common.VT","id":2,"name":"VT","namespace":"zict.buffer.Buffer","upper_bound":"builtins.object","values":[],"variance":0}],"extra_attrs":null,"type_ref":"zict.buffer.Buffer"},"builtins.float"],"bound_args":[],"def_extras":{"first_arg":"self"},"fallback":"builtins.function","from_concatenate":false,"implicit":false,"imprecise_arg_kinds":false,"is_ellipsis_args":false,"name":"offset of Buffer","ret_type":{".class":"NoneType"},"type_guard":null,"type_is":null,"unpack_kwargs":false,"variables":[]}},"is_overload":false,"var":{".class":"Var","flags":["is_inferred"],"fullname":"","name":"offset","type":null}}],"type":{".class":"Overloaded","items":[{".class":"CallableType","arg_kinds":[0],"arg_names":["self"],"arg_types":[{".class":"Instance","args":[{".class":"TypeVarType","default":{".class":"AnyType","missing_import_name":null,"source_any":null,"type_of_any":4},"fullname":"zict.common.KT","id":1,"name":"KT","namespace":"zict.buffer.Buffer","upper_bound":"builtins.object","values":[],"variance":0},{".class":"TypeVarType","default":{".class":"AnyType","missing_import_name":null,"source_any":null,"type_of_any":4},"fullname":"zict.common.VT","id":2,"name":"VT","namespace":"zict.buffer.Buffer","upper_bound":"builtins.object","values":[],"variance":0}],"extra_attrs":null,"type_ref":"zict.buffer.Buffer"}],"bound_args":[],"def_extras":{"first_arg":"self"},"fallback":"builtins.function","from_concatenate":false,"implicit":false,"imprecise_arg_kinds":false,"is_ellipsis_args":false,"name":"offset of Buffer","ret_type":"builtins.float","type_guard":null,"type_is":null,"unpack_kwargs":false,"variables":[]}]}}},"set_noevict":{".class":"SymbolTableNode","kind":"Mdef","node":{".class":"Decorator","func":{".class":"FuncDef","abstract_status":0,"arg_kinds":[0,0,0],"arg_names":["self","key","value"],"dataclass_transform_spec":null,"deprecated":null,"flags":["is_decorated"],"fullname":"zict.buffer.Buffer.set_noevict","name":"set_noevict","type":{".class":"CallableType","arg_kinds":[0,0,0],"arg_names":["self","key","value"],"arg_types":[{".class":"Instance","args":[{".class":"TypeVarType","default":{".class":"AnyType","missing_import_name":null,"source_any":null,"type_of_any":4},"fullname":"zict.common.KT","id":1,"name":"KT","namespace":"zict.buffer.Buffer","upper_bound":"builtins.object","values":[],"variance":0},{".class":"TypeVarType","default":{".class":"AnyType","missing_import_name":null,"source_any":null,"type_of_any":4},"fullname":"zict.common.VT","id":2,"name":"VT","namespace":"zict.buffer.Buffer","upper_bound":"builtins.object","values":[],"variance":0}],"extra_attrs":null,"type_ref":"zict.buffer.Buffer"},{".class":"TypeVarType","default":{".class":"AnyType","missing_import_name":null,"source_any":null,"type_of_any":4},"fullname":"zict.common.KT","id":1,"name":"KT","namespace":"zict.buffer.Buffer","upper_bound":"builtins.object","values":[],"variance":0},{".class":"TypeVarType","default":{".class":"AnyType","missing_import_name":null,"source_any":null,"type_of_any":4},"fullname":"zict.common.VT","id":2,"name":"VT","namespace":"zict.buffer.Buffer","upper_bound":"builtins.object","values":[],"variance":0}],"bound_args":[],"def_extras":{"first_arg":"self"},"fallback":"builtins.function","from_concatenate":false,"implicit":false,"imprecise_arg_kinds":false,"is_ellipsis_args":false,"name":"set_noevict of Buffer","ret_type":{".class":"NoneType"},"type_guard":null,"type_is":null,"unpack_kwargs":false,"variables":[]}},"is_overload":false,"var":{".class":"Var","flags":["is_initialized_in_class","is_ready","is_inferred"],"fullname":"zict.buffer.Buffer.set_noevict","name":"set_noevict","type":{".class":"CallableType","arg_kinds":[0,0,0],"arg_names":["self","key","value"],"arg_types":[{".class":"Instance","args":[{".class":"TypeVarType","default":{".class":"AnyType","missing_import_name":null,"source_any":null,"type_of_any":4},"fullname":"zict.common.KT","id":1,"name":"KT","namespace":"zict.buffer.Buffer","upper_bound":"builtins.object","values":[],"variance":0},{".class":"TypeVarType","default":{".class":"AnyType","missing_import_name":null,"source_any":null,"type_of_any":4},"fullname":"zict.common.VT","id":2,"name":"VT","namespace":"zict.buffer.Buffer","upper_bound":"builtins.object","values":[],"variance":0}],"extra_attrs":null,"type_ref":"zict.buffer.Buffer"},{".class":"TypeVarType","default":{".class":"AnyType","missing_import_name":null,"source_any":null,"type_of_any":4},"fullname":"zict.common.KT","id":1,"name":"KT","namespace":"zict.buffer.Buffer","upper_bound":"builtins.object","values":[],"variance":0},{".class":"TypeVarType","default":{".class":"AnyType","missing_import_name":null,"source_any":null,"type_of_any":4},"fullname":"zict.common.VT","id":2,"name":"VT","namespace":"zict.buffer.Buffer","upper_bound":"builtins.object","values":[],"variance":0}],"bound_args":[],"def_extras":{},"fallback":"builtins.function","from_concatenate":false,"implicit":false,"imprecise_arg_kinds":false,"is_ellipsis_args":false,"name":"set_noevict of Buffer","ret_type":{".class":"NoneType"},"type_guard":null,"type_is":null,"unpack_kwargs":false,"variables":[]}}}},"slow":{".class":"SymbolTableNode","kind":"Mdef","node":{".class":"Var","flags":["is_initialized_in_class","is_ready"],"fullname":"zict.buffer.Buffer.slow","name":"slow","type":{".class":"Instance","args":[{".class":"TypeVarType","default":{".class":"AnyType","missing_import_name":null,"source_any":null,"type_of_any":4},"fullname":"zict.common.KT","id":1,"name":"KT","namespace":"zict.buffer.Buffer","upper_bound":"builtins.object","values":[],"variance":0},{".class":"TypeVarType","default":{".class":"AnyType","missing_import_name":null,"source_any":null,"type_of_any":4},"fullname":"zict.common.VT","id":2,"name":"VT","namespace":"zict.buffer.Buffer","upper_bound":"builtins.object","values":[],"variance":0}],"extra_attrs":null,"type_ref":"typing.MutableMapping"}}},"slow_to_fast":{".class":"SymbolTableNode","kind":"Mdef","node":{".class":"FuncDef","abstract_status":0,"arg_kinds":[0,0],"arg_names":["self","key"],"dataclass_transform_spec":null,"deprecated":null,"flags":[],"fullname":"zict.buffer.Buffer.slow_to_fast","name":"slow_to_fast","type":{".class":"CallableType","arg_kinds":[0,0],"arg_names":["self","key"],"arg_types":[{".class":"Instance","args":[{".class":"TypeVarType","default":{".class":"AnyType","missing_import_name":null,"source_any":null,"type_of_any":4},"fullname":"zict.common.KT","id":1,"name":"KT","namespace":"zict.buffer.Buffer","upper_bound":"builtins.object","values":[],"variance":0},{".class":"TypeVarType","default":{".class":"AnyType","missing_import_name":null,"source_any":null,"type_of_any":4},"fullname":"zict.common.VT","id":2,"name":"VT","namespace":"zict.buffer.Buffer","upper_bound":"builtins.object","values":[],"variance":0}],"extra_attrs":null,"type_ref":"zict.buffer.Buffer"},{".class":"TypeVarType","default":{".class":"AnyType","missing_import_name":null,"source_any":null,"type_of_any":4},"fullname":"zict.common.KT","id":1,"name":"KT","namespace":"zict.buffer.Buffer","upper_bound":"builtins.object","values":[],"variance":0}],"bound_args":[],"def_extras":{"first_arg":"self"},"fallback":"builtins.function","from_concatenate":false,"implicit":false,"imprecise_arg_kinds":false,"is_ellipsis_args":false,"name":"slow_to_fast of Buffer","ret_type":{".class":"TypeVarType","default":{".class":"AnyType","missing_import_name":null,"source_any":null,"type_of_any":4},"fullname":"zict.common.VT","id":2,"name":"VT","namespace":"zict.buffer.Buffer","upper_bound":"builtins.object","values":[],"variance":0},"type_guard":null,"type_is":null,"unpack_kwargs":false,"variables":[]}}},"slow_to_fast_callbacks":{".class":"SymbolTableNode","kind":"Mdef","node":{".class":"Var","flags":["is_initialized_in_class","is_ready"],"fullname":"zict.buffer.Buffer.slow_to_fast_callbacks","name":"slow_to_fast_callbacks","type":{".class":"Instance","args":[{".class":"CallableType","arg_kinds":[0,0],"arg_names":[null,null],"arg_types":[{".class":"TypeVarType","default":{".class":"AnyType","missing_import_name":null,"source_any":null,"type_of_any":4},"fullname":"zict.common.KT","id":1,"name":"KT","namespace":"zict.buffer.Buffer","upper_bound":"builtins.object","values":[],"variance":0},{".class":"TypeVarType","default":{".class":"AnyType","missing_import_name":null,"source_any":null,"type_of_any":4},"fullname":"zict.common.VT","id":2,"name":"VT","namespace":"zict.buffer.Buffer","upper_bound":"builtins.object","values":[],"variance":0}],"bound_args":[],"def_extras":{},"fallback":"builtins.function","from_concatenate":false,"implicit":false,"imprecise_arg_kinds":false,"is_ellipsis_args":false,"name":null,"ret_type":{".class":"NoneType"},"type_guard":null,"type_is":null,"unpack_kwargs":false,"variables":[]}],"extra_attrs":null,"type_ref":"builtins.list"}}},"values":{".class":"SymbolTableNode","kind":"Mdef","node":{".class":"FuncDef","abstract_status":0,"arg_kinds":[0],"arg_names":["self"],"dataclass_transform_spec":null,"deprecated":null,"flags":[],"fullname":"zict.buffer.Buffer.values","name":"values","type":{".class":"CallableType","arg_kinds":[0],"arg_names":["self"],"arg_types":[{".class":"Instance","args":[{".class":"TypeVarType","default":{".class":"AnyType","missing_import_name":null,"source_any":null,"type_of_any":4},"fullname":"zict.common.KT","id":1,"name":"KT","namespace":"zict.buffer.Buffer","upper_bound":"builtins.object","values":[],"variance":0},{".class":"TypeVarType","default":{".class":"AnyType","missing_import_name":null,"source_any":null,"type_of_any":4},"fullname":"zict.common.VT","id":2,"name":"VT","namespace":"zict.buffer.Buffer","upper_bound":"builtins.object","values":[],"variance":0}],"extra_attrs":null,"type_ref":"zict.buffer.Buffer"}],"bound_args":[],"def_extras":{"first_arg":"self"},"fallback":"builtins.function","from_concatenate":false,"implicit":false,"imprecise_arg_kinds":false,"is_ellipsis_args":false,"name":"values of Buffer","ret_type":{".class":"Instance","args":[{".class":"TypeVarType","default":{".class":"AnyType","missing_import_name":null,"source_any":null,"type_of_any":4},"fullname":"zict.common.VT","id":2,"name":"VT","namespace":"zict.buffer.Buffer","upper_bound":"builtins.object","values":[],"variance":0}],"extra_attrs":null,"type_ref":"typing.ValuesView"},"type_guard":null,"type_is":null,"unpack_kwargs":false,"variables":[]}}},"weight":{".class":"SymbolTableNode","kind":"Mdef","node":{".class":"Var","flags":["is_initialized_in_class","is_ready"],"fullname":"zict.buffer.Buffer.weight","name":"weight","type":{".class":"CallableType","arg_kinds":[0,0],"arg_names":[null,null],"arg_types":[{".class":"TypeVarType","default":{".class":"AnyType","missing_import_name":null,"source_any":null,"type_of_any":4},"fullname":"zict.common.KT","id":1,"name":"KT","namespace":"zict.buffer.Buffer","upper_bound":"builtins.object","values":[],"variance":0},{".class":"TypeVarType","default":{".class":"AnyType","missing_import_name":null,"source_any":null,"type_of_any":4},"fullname":"zict.common.VT","id":2,"name":"VT","namespace":"zict.buffer.Buffer","upper_bound":"builtins.object","values":[],"variance":0}],"bound_args":[],"def_extras":{},"fallback":"builtins.function","from_concatenate":false,"implicit":false,"imprecise_arg_kinds":false,"is_ellipsis_args":false,"name":null,"ret_type":"builtins.float","type_guard":null,"type_is":null,"unpack_kwargs":false,"variables":[]}}}},"self_type":{".class":"TypeVarType","default":{".class":"AnyType","missing_import_name":null,"source_any":null,"type_of_any":4},"fullname":"zict.buffer.Buffer.Self","id":0,"name":"Self","namespace":"","upper_bound":{".class":"Instance","args":[{".class":"TypeVarType","default":{".class":"AnyType","missing_import_name":null,"source_any":null,"type_of_any":4},"fullname":"zict.common.KT","id":1,"name":"KT","namespace":"zict.buffer.Buffer","upper_bound":"builtins.object","values":[],"variance":0},{".class":"TypeVarType","default":{".class":"AnyType","missing_import_name":null,"source_any":null,"type_of_any":4},"fullname":"zict.common.VT","id":2,"name":"VT","namespace":"zict.buffer.Buffer","upper_bound":"builtins.object","values":[],"variance":0}],"extra_attrs":null,"type_ref":"zict.buffer.Buffer"},"values":[],"variance":0},"slots":null,"tuple_type":null,"type_vars":["KT","VT"],"typeddict_type":null}},"BufferItemsView":{".class":"SymbolTableNode","kind":"Gdef","node":{".class":"TypeInfo","_promote":[],"abstract_attributes":[],"alt_promote":null,"bases":[{".class":"Instance","args":[{".class":"TypeVarType","default":{".class":"AnyType","missing_import_name":null,"source_any":null,"type_of_any":4},"fullname":"zict.common.KT","id":1,"name":"KT","namespace":"zict.buffer.BufferItemsView","upper_bound":"builtins.object","values":[],"variance":0},{".class":"TypeVarType","default":{".class":"AnyType","missing_import_name":null,"source_any":null,"type_of_any":4},"fullname":"zict.common.VT","id":2,"name":"VT","namespace":"zict.buffer.BufferItemsView","upper_bound":"builtins.object","values":[],"variance":0}],"extra_attrs":null,"type_ref":"typing.ItemsView"}],"dataclass_transform_spec":null,"declared_metaclass":null,"defn":{".class":"ClassDef","fullname":"zict.buffer.BufferItemsView","name":"BufferItemsView","type_vars":[{".class":"TypeVarType","default":{".class":"AnyType","missing_import_name":null,"source_any":null,"type_of_any":4},"fullname":"zict.common.KT","id":1,"name":"KT","namespace":"zict.buffer.BufferItemsView","upper_bound":"builtins.object","values":[],"variance":0},{".class":"TypeVarType","default":{".class":"AnyType","missing_import_name":null,"source_any":null,"type_of_any":4},"fullname":"zict.common.VT","id":2,"name":"VT","namespace":"zict.buffer.BufferItemsView","upper_bound":"builtins.object","values":[],"variance":0}]},"deletable_attributes":[],"deprecated":null,"flags":[],"fullname":"zict.buffer.BufferItemsView","has_param_spec_type":false,"metaclass_type":"abc.ABCMeta","metadata":{},"module_name":"zict.buffer","mro":["zict.buffer.BufferItemsView","typing.ItemsView","typing.MappingView","typing.Sized","typing.AbstractSet","typing.Collection","typing.Iterable","typing.Container","builtins.object"],"names":{".class":"SymbolTable","__iter__":{".class":"SymbolTableNode","kind":"Mdef","node":{".class":"FuncDef","abstract_status":0,"arg_kinds":[0],"arg_names":[null],"dataclass_transform_spec":null,"deprecated":null,"flags":[],"fullname":"zict.buffer.BufferItemsView.__iter__","name":"__iter__","type":{".class":"CallableType","arg_kinds":[0],"arg_names":[null],"arg_types":[{".class":"Instance","args":[{".class":"TypeVarType","default":{".class":"AnyType","missing_import_name":null,"source_any":null,"type_of_any":4},"fullname":"zict.common.KT","id":1,"name":"KT","namespace":"zict.buffer.BufferItemsView","upper_bound":"builtins.object","values":[],"variance":0},{".class":"TypeVarType","default":{".class":"AnyType","missing_import_name":null,"source_any":null,"type_of_any":4},"fullname":"zict.common.VT","id":2,"name":"VT","namespace":"zict.buffer.BufferItemsView","upper_bound":"builtins.object","values":[],"variance":0}],"extra_attrs":null,"type_ref":"zict.buffer.BufferItemsView"}],"bound_args":[],"def_extras":{"first_arg":"self"},"fallback":"builtins.function","from_concatenate":false,"implicit":false,"imprecise_arg_kinds":false,"is_ellipsis_args":false,"name":"__iter__ of BufferItemsView","ret_type":{".class":"Instance","args":[{".class":"TupleType","implicit":false,"items":[{".class":"TypeVarType","default":{".class":"AnyType","missing_import_name":null,"source_any":null,"type_of_any":4},"fullname":"zict.common.KT","id":1,"name":"KT","namespace":"zict.buffer.BufferItemsView","upper_bound":"builtins.object","values":[],"variance":0},{".class":"TypeVarType","default":{".class":"AnyType","missing_import_name":null,"source_any":null,"type_of_any":4},"fullname":"zict.common.VT","id":2,"name":"VT","namespace":"zict.buffer.BufferItemsView","upper_bound":"builtins.object","values":[],"variance":0}],"partial_fallback":{".class":"Instance","args":[{".class":"AnyType","missing_import_name":null,"source_any":null,"type_of_any":6}],"extra_attrs":null,"type_ref":"builtins.tuple"}}],"extra_attrs":null,"type_ref":"typing.Iterator"},"type_guard":null,"type_is":null,"unpack_kwargs":false,"variables":[]}}},"__slots__":{".class":"SymbolTableNode","kind":"Mdef","node":{".class":"Var","flags":["is_initialized_in_class","is_inferred","has_explicit_value","allow_incompatible_override"],"fullname":"zict.buffer.BufferItemsView.__slots__","name":"__slots__","type":{".class":"TupleType","implicit":false,"items":[],"partial_fallback":{".class":"Instance","args":[{".class":"AnyType","missing_import_name":null,"source_any":null,"type_of_any":6}],"extra_attrs":null,"type_ref":"builtins.tuple"}}}},"_mapping":{".class":"SymbolTableNode","kind":"Mdef","node":{".class":"Var","flags":["is_initialized_in_class","is_ready"],"fullname":"zict.buffer.BufferItemsView._mapping","name":"_mapping","type":{".class":"Instance","args":[{".class":"AnyType","missing_import_name":null,"source_any":null,"type_of_any":4},{".class":"AnyType","missing_import_name":null,"source_any":null,"type_of_any":4}],"extra_attrs":null,"type_ref":"zict.buffer.Buffer"}}}},"self_type":{".class":"TypeVarType","default":{".class":"AnyType","missing_import_name":null,"source_any":null,"type_of_any":4},"fullname":"zict.buffer.BufferItemsView.Self","id":0,"name":"Self","namespace":"","upper_bound":{".class":"Instance","args":[{".class":"TypeVarType","default":{".class":"AnyType","missing_import_name":null,"source_any":null,"type_of_any":4},"fullname":"zict.common.KT","id":1,"name":"KT","namespace":"zict.buffer.BufferItemsView","upper_bound":"builtins.object","values":[],"variance":0},{".class":"TypeVarType","default":{".class":"AnyType","missing_import_name":null,"source_any":null,"type_of_any":4},"fullname":"zict.common.VT","id":2,"name":"VT","namespace":"zict.buffer.BufferItemsView","upper_bound":"builtins.object","values":[],"variance":0}],"extra_attrs":null,"type_ref":"zict.buffer.BufferItemsView"},"values":[],"variance":0},"slots":null,"tuple_type":null,"type_vars":["KT","VT"],"typeddict_type":null}},"BufferValuesView":{".class":"SymbolTableNode","kind":"Gdef","node":{".class":"TypeInfo","_promote":[],"abstract_attributes":[],"alt_promote":null,"bases":[{".class":"Instance","args":[{".class":"TypeVarType","default":{".class":"AnyType","missing_import_name":null,"source_any":null,"type_of_any":4},"fullname":"zict.common.VT","id":1,"name":"VT","namespace":"zict.buffer.BufferValuesView","upper_bound":"builtins.object","values":[],"variance":0}],"extra_attrs":null,"type_ref":"typing.ValuesView"}],"dataclass_transform_spec":null,"declared_metaclass":null,"defn":{".class":"ClassDef","fullname":"zict.buffer.BufferValuesView","name":"BufferValuesView","type_vars":[{".class":"TypeVarType","default":{".class":"AnyType","missing_import_name":null,"source_any":null,"type_of_any":4},"fullname":"zict.common.VT","id":1,"name":"VT","namespace":"zict.buffer.BufferValuesView","upper_bound":"builtins.object","values":[],"variance":0}]},"deletable_attributes":[],"deprecated":null,"flags":[],"fullname":"zict.buffer.BufferValuesView","has_param_spec_type":false,"metaclass_type":"abc.ABCMeta","metadata":{},"module_name":"zict.buffer","mro":["zict.buffer.BufferValuesView","typing.ValuesView","typing.MappingView","typing.Sized","typing.Collection","typing.Iterable","typing.Container","builtins.object"],"names":{".class":"SymbolTable","__contains__":{".class":"SymbolTableNode","kind":"Mdef","node":{".class":"FuncDef","abstract_status":0,"arg_kinds":[0,0],"arg_names":[null,null],"dataclass_transform_spec":null,"deprecated":null,"flags":[],"fullname":"zict.buffer.BufferValuesView.__contains__","name":"__contains__","type":{".class":"CallableType","arg_kinds":[0,0],"arg_names":[null,null],"arg_types":[{".class":"Instance","args":[{".class":"TypeVarType","default":{".class":"AnyType","missing_import_name":null,"source_any":null,"type_of_any":4},"fullname":"zict.common.VT","id":1,"name":"VT","namespace":"zict.buffer.BufferValuesView","upper_bound":"builtins.object","values":[],"variance":0}],"extra_attrs":null,"type_ref":"zict.buffer.BufferValuesView"},"builtins.object"],"bound_args":[],"def_extras":{"first_arg":"self"},"fallback":"builtins.function","from_concatenate":false,"implicit":false,"imprecise_arg_kinds":false,"is_ellipsis_args":false,"name":"__contains__ of BufferValuesView","ret_type":"builtins.bool","type_guard":null,"type_is":null,"unpack_kwargs":false,"variables":[]}}},"__iter__":{".class":"SymbolTableNode","kind":"Mdef","node":{".class":"FuncDef","abstract_status":0,"arg_kinds":[0],"arg_names":[null],"dataclass_transform_spec":null,"deprecated":null,"flags":[],"fullname":"zict.buffer.BufferValuesView.__iter__","name":"__iter__","type":{".class":"CallableType","arg_kinds":[0],"arg_names":[null],"arg_types":[{".class":"Instance","args":[{".class":"TypeVarType","default":{".class":"AnyType","missing_import_name":null,"source_any":null,"type_of_any":4},"fullname":"zict.common.VT","id":1,"name":"VT","namespace":"zict.buffer.BufferValuesView","upper_bound":"builtins.object","values":[],"variance":0}],"extra_attrs":null,"type_ref":"zict.buffer.BufferValuesView"}],"bound_args":[],"def_extras":{"first_arg":"self"},"fallback":"builtins.function","from_concatenate":false,"implicit":false,"imprecise_arg_kinds":false,"is_ellipsis_args":false,"name":"__iter__ of BufferValuesView","ret_type":{".class":"Instance","args":[{".class":"TypeVarType","default":{".class":"AnyType","missing_import_name":null,"source_any":null,"type_of_any":4},"fullname":"zict.common.VT","id":1,"name":"VT","namespace":"zict.buffer.BufferValuesView","upper_bound":"builtins.object","values":[],"variance":0}],"extra_attrs":null,"type_ref":"typing.Iterator"},"type_guard":null,"type_is":null,"unpack_kwargs":false,"variables":[]}}},"__slots__":{".class":"SymbolTableNode","kind":"Mdef","node":{".class":"Var","flags":["is_initialized_in_class","is_inferred","has_explicit_value","allow_incompatible_override"],"fullname":"zict.buffer.BufferValuesView.__slots__","name":"__slots__","type":{".class":"TupleType","implicit":false,"items":[],"partial_fallback":{".class":"Instance","args":[{".class":"AnyType","missing_import_name":null,"source_any":null,"type_of_any":6}],"extra_attrs":null,"type_ref":"builtins.tuple"}}}},"_mapping":{".class":"SymbolTableNode","kind":"Mdef","node":{".class":"Var","flags":["is_initialized_in_class","is_ready"],"fullname":"zict.buffer.BufferValuesView._mapping","name":"_mapping","type":{".class":"Instance","args":[{".class":"AnyType","missing_import_name":null,"source_any":null,"type_of_any":4},{".class":"AnyType","missing_import_name":null,"source_any":null,"type_of_any":4}],"extra_attrs":null,"type_ref":"zict.buffer.Buffer"}}}},"self_type":{".class":"TypeVarType","default":{".class":"AnyType","missing_import_name":null,"source_any":null,"type_of_any":4},"fullname":"zict.buffer.BufferValuesView.Self","id":0,"name":"Self","namespace":"","upper_bound":{".class":"Instance","args":[{".class":"TypeVarType","default":{".class":"AnyType","missing_import_name":null,"source_any":null,"type_of_any":4},"fullname":"zict.common.VT","id":1,"name":"VT","namespace":"zict.buffer.BufferValuesView","upper_bound":"builtins.object","values":[],"variance":0}],"extra_attrs":null,"type_ref":"zict.buffer.BufferValuesView"},"values":[],"variance":0},"slots":null,"tuple_type":null,"type_vars":["VT"],"typeddict_type":null}},"Callable":{".class":"SymbolTableNode","cross_ref":"typing.Callable","kind":"Gdef"},"ItemsView":{".class":"SymbolTableNode","cross_ref":"typing.ItemsView","kind":"Gdef"},"Iterator":{".class":"SymbolTableNode","cross_ref":"typing.Iterator","kind":"Gdef"},"KT":{".class":"SymbolTableNode","cross_ref":"zict.common.KT","kind":"Gdef"},"LRU":{".class":"SymbolTableNode","cross_ref":"zict.lru.LRU","kind":"Gdef"},"MutableMapping":{".class":"SymbolTableNode","cross_ref":"typing.MutableMapping","kind":"Gdef"},"VT":{".class":"SymbolTableNode","cross_ref":"zict.common.VT","kind":"Gdef"},"ValuesView":{".class":"SymbolTableNode","cross_ref":"typing.ValuesView","kind":"Gdef"},"ZictBase":{".class":"SymbolTableNode","cross_ref":"zict.common.ZictBase","kind":"Gdef"},"__annotations__":{".class":"SymbolTableNode","kind":"Gdef","node":{".class":"Var","flags":["is_ready"],"fullname":"zict.buffer.__annotations__","name":"__annotations__","type":{".class":"Instance","args":["builtins.str",{".class":"AnyType","missing_import_name":null,"source_any":null,"type_of_any":6}],"extra_attrs":null,"type_ref":"builtins.dict"}}},"__doc__":{".class":"SymbolTableNode","kind":"Gdef","node":{".class":"Var","flags":["is_ready"],"fullname":"zict.buffer.__doc__","name":"__doc__","type":"builtins.str"}},"__file__":{".class":"SymbolTableNode","kind":"Gdef","node":{".class":"Var","flags":["is_ready"],"fullname":"zict.buffer.__file__","name":"__file__","type":"builtins.str"}},"__name__":{".class":"SymbolTableNode","kind":"Gdef","node":{".class":"Var","flags":["is_ready"],"fullname":"zict.buffer.__name__","name":"__name__","type":"builtins.str"}},"__package__":{".class":"SymbolTableNode","kind":"Gdef","node":{".class":"Var","flags":["is_ready"],"fullname":"zict.buffer.__package__","name":"__package__","type":"builtins.str"}},"__spec__":{".class":"SymbolTableNode","kind":"Gdef","node":{".class":"Var","flags":["is_ready"],"fullname":"zict.buffer.__spec__","name":"__spec__","type":"_frozen_importlib.ModuleSpec"}},"annotations":{".class":"SymbolTableNode","cross_ref":"__future__.annotations","kind":"Gdef"},"chain":{".class":"SymbolTableNode","cross_ref":"itertools.chain","kind":"Gdef"},"close":{".class":"SymbolTableNode","cross_ref":"zict.common.close","kind":"Gdef"},"discard":{".class":"SymbolTableNode","cross_ref":"zict.common.discard","kind":"Gdef"},"flush":{".class":"SymbolTableNode","cross_ref":"zict.common.flush","kind":"Gdef"},"locked":{".class":"SymbolTableNode","cross_ref":"zict.common.locked","kind":"Gdef"}},"path":"C:\\ProgramData\\anaconda3\\Lib\\site-packages\\zict\\buffer.py"}