{".class":"MypyFile","_fullname":"alembic.autogenerate.compare","future_import_flags":["annotations"],"is_partial_stub_package":false,"is_stub":false,"names":{".class":"SymbolTable","AutogenContext":{".class":"SymbolTableNode","cross_ref":"alembic.autogenerate.api.AutogenContext","kind":"Gdef"},"MigrationScript":{".class":"SymbolTableNode","cross_ref":"alembic.operations.ops.MigrationScript","kind":"Gdef"},"Plugin":{".class":"SymbolTableNode","cross_ref":"alembic.runtime.plugins.Plugin","kind":"Gdef"},"TYPE_CHECKING":{".class":"SymbolTableNode","cross_ref":"typing.TYPE_CHECKING","kind":"Gdef"},"UpgradeOps":{".class":"SymbolTableNode","cross_ref":"alembic.operations.ops.UpgradeOps","kind":"Gdef"},"__annotations__":{".class":"SymbolTableNode","kind":"Gdef","node":{".class":"Var","flags":["is_ready"],"fullname":"alembic.autogenerate.compare.__annotations__","name":"__annotations__","type":{".class":"Instance","args":["builtins.str",{".class":"AnyType","missing_import_name":null,"source_any":null,"type_of_any":6}],"extra_attrs":null,"type_ref":"builtins.dict"}}},"__doc__":{".class":"SymbolTableNode","kind":"Gdef","node":{".class":"Var","flags":["is_ready"],"fullname":"alembic.autogenerate.compare.__doc__","name":"__doc__","type":"builtins.str"}},"__file__":{".class":"SymbolTableNode","kind":"Gdef","node":{".class":"Var","flags":["is_ready"],"fullname":"alembic.autogenerate.compare.__file__","name":"__file__","type":"builtins.str"}},"__name__":{".class":"SymbolTableNode","kind":"Gdef","node":{".class":"Var","flags":["is_ready"],"fullname":"alembic.autogenerate.compare.__name__","name":"__name__","type":"builtins.str"}},"__package__":{".class":"SymbolTableNode","kind":"Gdef","node":{".class":"Var","flags":["is_ready"],"fullname":"alembic.autogenerate.compare.__package__","name":"__package__","type":"builtins.str"}},"__path__":{".class":"SymbolTableNode","kind":"Gdef","node":{".class":"Var","flags":["is_ready"],"fullname":"alembic.autogenerate.compare.__path__","name":"__path__","type":{".class":"Instance","args":["builtins.str"],"extra_attrs":null,"type_ref":"builtins.list"}}},"__spec__":{".class":"SymbolTableNode","kind":"Gdef","node":{".class":"Var","flags":["is_ready"],"fullname":"alembic.autogenerate.compare.__spec__","name":"__spec__","type":"_frozen_importlib.ModuleSpec"}},"_populate_migration_script":{".class":"SymbolTableNode","kind":"Gdef","node":{".class":"FuncDef","abstract_status":0,"arg_kinds":[0,0],"arg_names":["autogen_context","migration_script"],"dataclass_transform_spec":null,"deprecated":null,"flags":[],"fullname":"alembic.autogenerate.compare._populate_migration_script","name":"_populate_migration_script","type":{".class":"CallableType","arg_kinds":[0,0],"arg_names":["autogen_context","migration_script"],"arg_types":["alembic.autogenerate.api.AutogenContext","alembic.operations.ops.MigrationScript"],"bound_args":[],"def_extras":{"first_arg":null},"fallback":"builtins.function","from_concatenate":false,"implicit":false,"imprecise_arg_kinds":false,"is_ellipsis_args":false,"name":"_populate_migration_script","ret_type":{".class":"NoneType"},"type_guard":null,"type_is":null,"unpack_kwargs":false,"variables":[]}}},"_produce_net_changes":{".class":"SymbolTableNode","kind":"Gdef","node":{".class":"FuncDef","abstract_status":0,"arg_kinds":[0,0],"arg_names":["autogen_context","upgrade_ops"],"dataclass_transform_spec":null,"deprecated":null,"flags":[],"fullname":"alembic.autogenerate.compare._produce_net_changes","name":"_produce_net_changes","type":{".class":"CallableType","arg_kinds":[0,0],"arg_names":["autogen_context","upgrade_ops"],"arg_types":["alembic.autogenerate.api.AutogenContext","alembic.operations.ops.UpgradeOps"],"bound_args":[],"def_extras":{"first_arg":null},"fallback":"builtins.function","from_concatenate":false,"implicit":false,"imprecise_arg_kinds":false,"is_ellipsis_args":false,"name":"_produce_net_changes","ret_type":{".class":"NoneType"},"type_guard":null,"type_is":null,"unpack_kwargs":false,"variables":[]}}},"annotations":{".class":"SymbolTableNode","cross_ref":"__future__.annotations","kind":"Gdef"},"comments":{".class":"SymbolTableNode","cross_ref":"alembic.autogenerate.compare.comments","kind":"Gdef"},"comparators":{".class":"SymbolTableNode","kind":"Gdef","node":{".class":"Var","flags":["is_inferred","has_explicit_value"],"fullname":"alembic.autogenerate.compare.comparators","name":"comparators","type":"alembic.util.langhelpers.PriorityDispatcher"}},"constraints":{".class":"SymbolTableNode","cross_ref":"alembic.autogenerate.compare.constraints","kind":"Gdef"},"log":{".class":"SymbolTableNode","kind":"Gdef","node":{".class":"Var","flags":["is_inferred","has_explicit_value"],"fullname":"alembic.autogenerate.compare.log","name":"log","type":"logging.Logger"}},"logging":{".class":"SymbolTableNode","cross_ref":"logging","kind":"Gdef"},"schema":{".class":"SymbolTableNode","cross_ref":"alembic.autogenerate.compare.schema","kind":"Gdef"},"server_defaults":{".class":"SymbolTableNode","cross_ref":"alembic.autogenerate.compare.server_defaults","kind":"Gdef"},"tables":{".class":"SymbolTableNode","cross_ref":"alembic.autogenerate.compare.tables","kind":"Gdef"},"types":{".class":"SymbolTableNode","cross_ref":"alembic.autogenerate.compare.types","kind":"Gdef"},"util":{".class":"SymbolTableNode","cross_ref":"alembic.util","kind":"Gdef"}},"path":"C:\\Users\\Pc\\AppData\\Roaming\\Python\\Python313\\site-packages\\alembic\\autogenerate\\compare\\__init__.py"}