{".class":"MypyFile","_fullname":"jupyter_server.files.handlers","future_import_flags":["annotations"],"is_partial_stub_package":false,"is_stub":false,"names":{".class":"SymbolTable","AUTH_RESOURCE":{".class":"SymbolTableNode","kind":"Gdef","node":{".class":"Var","flags":["is_ready","is_inferred","has_explicit_value"],"fullname":"jupyter_server.files.handlers.AUTH_RESOURCE","name":"AUTH_RESOURCE","type":"builtins.str"}},"Awaitable":{".class":"SymbolTableNode","cross_ref":"typing.Awaitable","kind":"Gdef"},"FilesHandler":{".class":"SymbolTableNode","kind":"Gdef","node":{".class":"TypeInfo","_promote":[],"abstract_attributes":[],"alt_promote":null,"bases":["jupyter_server.base.handlers.JupyterHandler","tornado.web.StaticFileHandler"],"dataclass_transform_spec":null,"declared_metaclass":null,"defn":{".class":"ClassDef","fullname":"jupyter_server.files.handlers.FilesHandler","name":"FilesHandler","type_vars":[]},"deletable_attributes":[],"deprecated":null,"flags":[],"fullname":"jupyter_server.files.handlers.FilesHandler","has_param_spec_type":false,"metaclass_type":null,"metadata":{},"module_name":"jupyter_server.files.handlers","mro":["jupyter_server.files.handlers.FilesHandler","jupyter_server.base.handlers.JupyterHandler","jupyter_server.base.handlers.AuthenticatedHandler","tornado.web.StaticFileHandler","tornado.web.RequestHandler","builtins.object"],"names":{".class":"SymbolTable","auth_resource":{".class":"SymbolTableNode","kind":"Mdef","node":{".class":"Var","flags":["is_initialized_in_class","is_inferred","has_explicit_value"],"fullname":"jupyter_server.files.handlers.FilesHandler.auth_resource","name":"auth_resource","type":"builtins.str"}},"content_security_policy":{".class":"SymbolTableNode","kind":"Mdef","node":{".class":"Decorator","func":{".class":"FuncDef","abstract_status":0,"arg_kinds":[0],"arg_names":["self"],"dataclass_transform_spec":null,"deprecated":null,"flags":["is_property","is_decorated"],"fullname":"jupyter_server.files.handlers.FilesHandler.content_security_policy","name":"content_security_policy","type":null},"is_overload":false,"var":{".class":"Var","flags":["is_initialized_in_class","is_property","is_ready","is_inferred"],"fullname":"jupyter_server.files.handlers.FilesHandler.content_security_policy","name":"content_security_policy","type":{".class":"CallableType","arg_kinds":[0],"arg_names":["self"],"arg_types":["jupyter_server.files.handlers.FilesHandler"],"bound_args":[],"def_extras":{"first_arg":"self"},"fallback":"builtins.function","from_concatenate":false,"implicit":true,"imprecise_arg_kinds":false,"is_ellipsis_args":false,"name":"content_security_policy of FilesHandler","ret_type":{".class":"AnyType","missing_import_name":null,"source_any":null,"type_of_any":1},"type_guard":null,"type_is":null,"unpack_kwargs":false,"variables":[]}}}},"get":{".class":"SymbolTableNode","kind":"Mdef","node":{".class":"Decorator","func":{".class":"FuncDef","abstract_status":0,"arg_kinds":[0,0,1],"arg_names":["self","path","include_body"],"dataclass_transform_spec":null,"deprecated":null,"flags":["is_coroutine","is_decorated"],"fullname":"jupyter_server.files.handlers.FilesHandler.get","name":"get","type":null},"is_overload":false,"var":{".class":"Var","flags":["is_initialized_in_class","is_ready","is_inferred"],"fullname":"jupyter_server.files.handlers.FilesHandler.get","name":"get","type":{".class":"CallableType","arg_kinds":[2,4],"arg_names":[null,null],"arg_types":[{".class":"AnyType","missing_import_name":null,"source_any":null,"type_of_any":2},{".class":"AnyType","missing_import_name":null,"source_any":null,"type_of_any":2}],"bound_args":[],"def_extras":{},"fallback":"builtins.function","from_concatenate":false,"implicit":false,"imprecise_arg_kinds":false,"is_ellipsis_args":true,"name":"get of FilesHandler","ret_type":{".class":"UnionType","items":[{".class":"Instance","args":[{".class":"NoneType"}],"extra_attrs":null,"type_ref":"typing.Awaitable"},{".class":"NoneType"}],"uses_pep604_syntax":false},"type_guard":null,"type_is":null,"unpack_kwargs":false,"variables":[]}}}},"head":{".class":"SymbolTableNode","kind":"Mdef","node":{".class":"Decorator","func":{".class":"FuncDef","abstract_status":0,"arg_kinds":[0,0],"arg_names":["self","path"],"dataclass_transform_spec":null,"deprecated":null,"flags":["is_decorated"],"fullname":"jupyter_server.files.handlers.FilesHandler.head","name":"head","type":{".class":"CallableType","arg_kinds":[0,0],"arg_names":["self","path"],"arg_types":["jupyter_server.files.handlers.FilesHandler","builtins.str"],"bound_args":[],"def_extras":{"first_arg":"self"},"fallback":"builtins.function","from_concatenate":false,"implicit":false,"imprecise_arg_kinds":false,"is_ellipsis_args":false,"name":"head of FilesHandler","ret_type":{".class":"UnionType","items":[{".class":"Instance","args":[{".class":"NoneType"}],"extra_attrs":null,"type_ref":"typing.Awaitable"},{".class":"NoneType"}],"uses_pep604_syntax":true},"type_guard":null,"type_is":null,"unpack_kwargs":false,"variables":[]}},"is_overload":false,"var":{".class":"Var","flags":["is_initialized_in_class","is_ready","is_inferred"],"fullname":"jupyter_server.files.handlers.FilesHandler.head","name":"head","type":{".class":"CallableType","arg_kinds":[2,4],"arg_names":[null,null],"arg_types":[{".class":"AnyType","missing_import_name":null,"source_any":null,"type_of_any":2},{".class":"AnyType","missing_import_name":null,"source_any":null,"type_of_any":2}],"bound_args":[],"def_extras":{},"fallback":"builtins.function","from_concatenate":false,"implicit":false,"imprecise_arg_kinds":false,"is_ellipsis_args":true,"name":"head of FilesHandler","ret_type":{".class":"UnionType","items":[{".class":"Instance","args":[{".class":"NoneType"}],"extra_attrs":null,"type_ref":"typing.Awaitable"},{".class":"NoneType"}],"uses_pep604_syntax":false},"type_guard":null,"type_is":null,"unpack_kwargs":false,"variables":[]}}}}},"self_type":{".class":"TypeVarType","default":{".class":"AnyType","missing_import_name":null,"source_any":null,"type_of_any":4},"fullname":"jupyter_server.files.handlers.FilesHandler.Self","id":0,"name":"Self","namespace":"","upper_bound":"jupyter_server.files.handlers.FilesHandler","values":[],"variance":0},"slots":null,"tuple_type":null,"type_vars":[],"typeddict_type":null}},"JupyterHandler":{".class":"SymbolTableNode","cross_ref":"jupyter_server.base.handlers.JupyterHandler","kind":"Gdef"},"TYPE_CHECKING":{".class":"SymbolTableNode","cross_ref":"typing.TYPE_CHECKING","kind":"Gdef"},"__annotations__":{".class":"SymbolTableNode","kind":"Gdef","node":{".class":"Var","flags":["is_ready"],"fullname":"jupyter_server.files.handlers.__annotations__","name":"__annotations__","type":{".class":"Instance","args":["builtins.str",{".class":"AnyType","missing_import_name":null,"source_any":null,"type_of_any":6}],"extra_attrs":null,"type_ref":"builtins.dict"}}},"__doc__":{".class":"SymbolTableNode","kind":"Gdef","node":{".class":"Var","flags":["is_ready"],"fullname":"jupyter_server.files.handlers.__doc__","name":"__doc__","type":"builtins.str"}},"__file__":{".class":"SymbolTableNode","kind":"Gdef","node":{".class":"Var","flags":["is_ready"],"fullname":"jupyter_server.files.handlers.__file__","name":"__file__","type":"builtins.str"}},"__name__":{".class":"SymbolTableNode","kind":"Gdef","node":{".class":"Var","flags":["is_ready"],"fullname":"jupyter_server.files.handlers.__name__","name":"__name__","type":"builtins.str"}},"__package__":{".class":"SymbolTableNode","kind":"Gdef","node":{".class":"Var","flags":["is_ready"],"fullname":"jupyter_server.files.handlers.__package__","name":"__package__","type":"builtins.str"}},"__spec__":{".class":"SymbolTableNode","kind":"Gdef","node":{".class":"Var","flags":["is_ready"],"fullname":"jupyter_server.files.handlers.__spec__","name":"__spec__","type":"_frozen_importlib.ModuleSpec"}},"annotations":{".class":"SymbolTableNode","cross_ref":"__future__.annotations","kind":"Gdef"},"authorized":{".class":"SymbolTableNode","cross_ref":"jupyter_server.auth.decorator.authorized","kind":"Gdef"},"decodebytes":{".class":"SymbolTableNode","cross_ref":"base64.decodebytes","kind":"Gdef"},"default_handlers":{".class":"SymbolTableNode","kind":"Gdef","node":{".class":"Var","flags":["is_ready","has_explicit_value"],"fullname":"jupyter_server.files.handlers.default_handlers","name":"default_handlers","type":{".class":"Instance","args":["jupyter_server.base.handlers.JupyterHandler"],"extra_attrs":null,"type_ref":"builtins.list"}}},"ensure_async":{".class":"SymbolTableNode","cross_ref":"jupyter_core.utils.ensure_async","kind":"Gdef"},"mimetypes":{".class":"SymbolTableNode","cross_ref":"mimetypes","kind":"Gdef"},"web":{".class":"SymbolTableNode","cross_ref":"tornado.web","kind":"Gdef"}},"path":"C:\\ProgramData\\anaconda3\\Lib\\site-packages\\jupyter_server\\files\\handlers.py"}