{".class":"MypyFile","_fullname":"conda.history","future_import_flags":["annotations"],"is_partial_stub_package":false,"is_stub":false,"names":{".class":"SymbolTable","CONDA_VERSION":{".class":"SymbolTableNode","cross_ref":"conda._version.__version__","kind":"Gdef"},"CondaHistoryError":{".class":"SymbolTableNode","cross_ref":"conda.exceptions.CondaHistoryError","kind":"Gdef"},"CondaHistoryWarning":{".class":"SymbolTableNode","kind":"Gdef","node":{".class":"TypeInfo","_promote":[],"abstract_attributes":[],"alt_promote":null,"bases":["builtins.Warning"],"dataclass_transform_spec":null,"declared_metaclass":null,"defn":{".class":"ClassDef","fullname":"conda.history.CondaHistoryWarning","name":"CondaHistoryWarning","type_vars":[]},"deletable_attributes":[],"deprecated":null,"flags":[],"fullname":"conda.history.CondaHistoryWarning","has_param_spec_type":false,"metaclass_type":null,"metadata":{},"module_name":"conda.history","mro":["conda.history.CondaHistoryWarning","builtins.Warning","builtins.Exception","builtins.BaseException","builtins.object"],"names":{".class":"SymbolTable"},"self_type":{".class":"TypeVarType","default":{".class":"AnyType","missing_import_name":null,"source_any":null,"type_of_any":4},"fullname":"conda.history.CondaHistoryWarning.Self","id":0,"name":"Self","namespace":"","upper_bound":"conda.history.CondaHistoryWarning","values":[],"variance":0},"slots":null,"tuple_type":null,"type_vars":[],"typeddict_type":null}},"DEFAULTS_CHANNEL_NAME":{".class":"SymbolTableNode","cross_ref":"conda.base.constants.DEFAULTS_CHANNEL_NAME","kind":"Gdef"},"EACCES":{".class":"SymbolTableNode","cross_ref":"errno.EACCES","kind":"Gdef"},"EPERM":{".class":"SymbolTableNode","cross_ref":"errno.EPERM","kind":"Gdef"},"EROFS":{".class":"SymbolTableNode","cross_ref":"errno.EROFS","kind":"Gdef"},"History":{".class":"SymbolTableNode","kind":"Gdef","node":{".class":"TypeInfo","_promote":[],"abstract_attributes":[],"alt_promote":null,"bases":["builtins.object"],"dataclass_transform_spec":null,"declared_metaclass":null,"defn":{".class":"ClassDef","fullname":"conda.history.History","name":"History","type_vars":[]},"deletable_attributes":[],"deprecated":null,"flags":[],"fullname":"conda.history.History","has_param_spec_type":false,"metaclass_type":null,"metadata":{},"module_name":"conda.history","mro":["conda.history.History","builtins.object"],"names":{".class":"SymbolTable","__enter__":{".class":"SymbolTableNode","kind":"Mdef","node":{".class":"FuncDef","abstract_status":0,"arg_kinds":[0],"arg_names":[null],"dataclass_transform_spec":null,"deprecated":null,"flags":[],"fullname":"conda.history.History.__enter__","name":"__enter__","type":null}},"__exit__":{".class":"SymbolTableNode","kind":"Mdef","node":{".class":"FuncDef","abstract_status":0,"arg_kinds":[0,0,0,0],"arg_names":[null,null,null,null],"dataclass_transform_spec":null,"deprecated":null,"flags":[],"fullname":"conda.history.History.__exit__","name":"__exit__","type":null}},"__init__":{".class":"SymbolTableNode","kind":"Mdef","node":{".class":"FuncDef","abstract_status":0,"arg_kinds":[0,0],"arg_names":["self","prefix"],"dataclass_transform_spec":null,"deprecated":null,"flags":[],"fullname":"conda.history.History.__init__","name":"__init__","type":null}},"_parse_comment_line":{".class":"SymbolTableNode","kind":"Mdef","node":{".class":"Decorator","func":{".class":"FuncDef","abstract_status":0,"arg_kinds":[0,0],"arg_names":["cls","line"],"dataclass_transform_spec":null,"deprecated":null,"flags":["is_class","is_decorated"],"fullname":"conda.history.History._parse_comment_line","name":"_parse_comment_line","type":null},"is_overload":false,"var":{".class":"Var","flags":["is_initialized_in_class","is_classmethod","is_ready","is_inferred"],"fullname":"conda.history.History._parse_comment_line","name":"_parse_comment_line","type":{".class":"CallableType","arg_kinds":[0,0],"arg_names":["cls","line"],"arg_types":[{".class":"TypeType","item":"conda.history.History"},{".class":"AnyType","missing_import_name":null,"source_any":null,"type_of_any":1}],"bound_args":[],"def_extras":{"first_arg":"cls"},"fallback":"builtins.function","from_concatenate":false,"implicit":true,"imprecise_arg_kinds":false,"is_ellipsis_args":false,"name":"_parse_comment_line of History","ret_type":{".class":"AnyType","missing_import_name":null,"source_any":null,"type_of_any":1},"type_guard":null,"type_is":null,"unpack_kwargs":false,"variables":[]}}}},"_parse_old_format_specs_string":{".class":"SymbolTableNode","kind":"Mdef","node":{".class":"Decorator","func":{".class":"FuncDef","abstract_status":0,"arg_kinds":[0],"arg_names":["specs_string"],"dataclass_transform_spec":null,"deprecated":null,"flags":["is_static","is_decorated"],"fullname":"conda.history.History._parse_old_format_specs_string","name":"_parse_old_format_specs_string","type":null},"is_overload":false,"var":{".class":"Var","flags":["is_initialized_in_class","is_staticmethod","is_ready","is_inferred"],"fullname":"conda.history.History._parse_old_format_specs_string","name":"_parse_old_format_specs_string","type":{".class":"CallableType","arg_kinds":[0],"arg_names":["specs_string"],"arg_types":[{".class":"AnyType","missing_import_name":null,"source_any":null,"type_of_any":1}],"bound_args":[],"def_extras":{"first_arg":null},"fallback":"builtins.function","from_concatenate":false,"implicit":true,"imprecise_arg_kinds":false,"is_ellipsis_args":false,"name":"_parse_old_format_specs_string of History","ret_type":{".class":"AnyType","missing_import_name":null,"source_any":null,"type_of_any":1},"type_guard":null,"type_is":null,"unpack_kwargs":false,"variables":[]}}}},"com_pat":{".class":"SymbolTableNode","kind":"Mdef","node":{".class":"Var","flags":["is_initialized_in_class","is_inferred","has_explicit_value"],"fullname":"conda.history.History.com_pat","name":"com_pat","type":{".class":"Instance","args":["builtins.str"],"extra_attrs":null,"type_ref":"re.Pattern"}}},"conda_v_pat":{".class":"SymbolTableNode","kind":"Mdef","node":{".class":"Var","flags":["is_initialized_in_class","is_inferred","has_explicit_value"],"fullname":"conda.history.History.conda_v_pat","name":"conda_v_pat","type":{".class":"Instance","args":["builtins.str"],"extra_attrs":null,"type_ref":"re.Pattern"}}},"construct_states":{".class":"SymbolTableNode","kind":"Mdef","node":{".class":"FuncDef","abstract_status":0,"arg_kinds":[0],"arg_names":["self"],"dataclass_transform_spec":null,"deprecated":null,"flags":[],"fullname":"conda.history.History.construct_states","name":"construct_states","type":null}},"file_is_empty":{".class":"SymbolTableNode","kind":"Mdef","node":{".class":"FuncDef","abstract_status":0,"arg_kinds":[0],"arg_names":["self"],"dataclass_transform_spec":null,"deprecated":null,"flags":[],"fullname":"conda.history.History.file_is_empty","name":"file_is_empty","type":null}},"get_requested_specs_map":{".class":"SymbolTableNode","kind":"Mdef","node":{".class":"FuncDef","abstract_status":0,"arg_kinds":[0],"arg_names":["self"],"dataclass_transform_spec":null,"deprecated":null,"flags":[],"fullname":"conda.history.History.get_requested_specs_map","name":"get_requested_specs_map","type":null}},"get_state":{".class":"SymbolTableNode","kind":"Mdef","node":{".class":"FuncDef","abstract_status":0,"arg_kinds":[0,1],"arg_names":["self","rev"],"dataclass_transform_spec":null,"deprecated":null,"flags":[],"fullname":"conda.history.History.get_state","name":"get_state","type":null}},"get_user_requests":{".class":"SymbolTableNode","kind":"Mdef","node":{".class":"FuncDef","abstract_status":0,"arg_kinds":[0],"arg_names":["self"],"dataclass_transform_spec":null,"deprecated":null,"flags":[],"fullname":"conda.history.History.get_user_requests","name":"get_user_requests","type":null}},"init_log_file":{".class":"SymbolTableNode","kind":"Mdef","node":{".class":"FuncDef","abstract_status":0,"arg_kinds":[0],"arg_names":["self"],"dataclass_transform_spec":null,"deprecated":null,"flags":[],"fullname":"conda.history.History.init_log_file","name":"init_log_file","type":null}},"meta_dir":{".class":"SymbolTableNode","implicit":true,"kind":"Mdef","node":{".class":"Var","flags":["is_inferred"],"fullname":"conda.history.History.meta_dir","name":"meta_dir","type":{".class":"AnyType","missing_import_name":null,"source_any":null,"type_of_any":1}}},"object_log":{".class":"SymbolTableNode","kind":"Mdef","node":{".class":"FuncDef","abstract_status":0,"arg_kinds":[0],"arg_names":["self"],"dataclass_transform_spec":null,"deprecated":null,"flags":[],"fullname":"conda.history.History.object_log","name":"object_log","type":null}},"parse":{".class":"SymbolTableNode","kind":"Mdef","node":{".class":"FuncDef","abstract_status":0,"arg_kinds":[0],"arg_names":["self"],"dataclass_transform_spec":null,"deprecated":null,"flags":[],"fullname":"conda.history.History.parse","name":"parse","type":{".class":"CallableType","arg_kinds":[0],"arg_names":["self"],"arg_types":["conda.history.History"],"bound_args":[],"def_extras":{"first_arg":"self"},"fallback":"builtins.function","from_concatenate":false,"implicit":false,"imprecise_arg_kinds":false,"is_ellipsis_args":false,"name":"parse of History","ret_type":{".class":"Instance","args":[{".class":"TupleType","implicit":false,"items":["builtins.str",{".class":"Instance","args":["builtins.str"],"extra_attrs":null,"type_ref":"builtins.set"},{".class":"Instance","args":["builtins.str"],"extra_attrs":null,"type_ref":"builtins.list"}],"partial_fallback":{".class":"Instance","args":[{".class":"AnyType","missing_import_name":null,"source_any":null,"type_of_any":6}],"extra_attrs":null,"type_ref":"builtins.tuple"}}],"extra_attrs":null,"type_ref":"builtins.list"},"type_guard":null,"type_is":null,"unpack_kwargs":false,"variables":[]}}},"path":{".class":"SymbolTableNode","implicit":true,"kind":"Mdef","node":{".class":"Var","flags":["is_inferred"],"fullname":"conda.history.History.path","name":"path","type":{".class":"AnyType","missing_import_name":null,"source_any":null,"type_of_any":1}}},"prefix":{".class":"SymbolTableNode","implicit":true,"kind":"Mdef","node":{".class":"Var","flags":["is_inferred"],"fullname":"conda.history.History.prefix","name":"prefix","type":{".class":"AnyType","missing_import_name":null,"source_any":null,"type_of_any":1}}},"print_log":{".class":"SymbolTableNode","kind":"Mdef","node":{".class":"FuncDef","abstract_status":0,"arg_kinds":[0],"arg_names":["self"],"dataclass_transform_spec":null,"deprecated":null,"flags":[],"fullname":"conda.history.History.print_log","name":"print_log","type":null}},"spec_pat":{".class":"SymbolTableNode","kind":"Mdef","node":{".class":"Var","flags":["is_initialized_in_class","is_inferred","has_explicit_value"],"fullname":"conda.history.History.spec_pat","name":"spec_pat","type":{".class":"Instance","args":["builtins.str"],"extra_attrs":null,"type_ref":"re.Pattern"}}},"update":{".class":"SymbolTableNode","kind":"Mdef","node":{".class":"FuncDef","abstract_status":0,"arg_kinds":[0],"arg_names":["self"],"dataclass_transform_spec":null,"deprecated":null,"flags":[],"fullname":"conda.history.History.update","name":"update","type":{".class":"CallableType","arg_kinds":[0],"arg_names":["self"],"arg_types":["conda.history.History"],"bound_args":[],"def_extras":{"first_arg":"self"},"fallback":"builtins.function","from_concatenate":false,"implicit":false,"imprecise_arg_kinds":false,"is_ellipsis_args":false,"name":"update of History","ret_type":{".class":"NoneType"},"type_guard":null,"type_is":null,"unpack_kwargs":false,"variables":[]}}},"write_changes":{".class":"SymbolTableNode","kind":"Mdef","node":{".class":"FuncDef","abstract_status":0,"arg_kinds":[0,0,0],"arg_names":["self","last_state","current_state"],"dataclass_transform_spec":null,"deprecated":null,"flags":[],"fullname":"conda.history.History.write_changes","name":"write_changes","type":null}},"write_specs":{".class":"SymbolTableNode","kind":"Mdef","node":{".class":"FuncDef","abstract_status":0,"arg_kinds":[0,1,1,1],"arg_names":["self","remove_specs","update_specs","neutered_specs"],"dataclass_transform_spec":null,"deprecated":null,"flags":[],"fullname":"conda.history.History.write_specs","name":"write_specs","type":null}}},"self_type":{".class":"TypeVarType","default":{".class":"AnyType","missing_import_name":null,"source_any":null,"type_of_any":4},"fullname":"conda.history.History.Self","id":0,"name":"Self","namespace":"","upper_bound":"conda.history.History","values":[],"variance":0},"slots":null,"tuple_type":null,"type_vars":[],"typeddict_type":null}},"MatchSpec":{".class":"SymbolTableNode","cross_ref":"conda.models.match_spec.MatchSpec","kind":"Gdef"},"NotWritableError":{".class":"SymbolTableNode","cross_ref":"conda.exceptions.NotWritableError","kind":"Gdef"},"PrefixData":{".class":"SymbolTableNode","cross_ref":"conda.core.prefix_data.PrefixData","kind":"Gdef"},"VersionOrder":{".class":"SymbolTableNode","cross_ref":"conda.models.version.VersionOrder","kind":"Gdef"},"__annotations__":{".class":"SymbolTableNode","kind":"Gdef","node":{".class":"Var","flags":["is_ready"],"fullname":"conda.history.__annotations__","name":"__annotations__","type":{".class":"Instance","args":["builtins.str",{".class":"AnyType","missing_import_name":null,"source_any":null,"type_of_any":6}],"extra_attrs":null,"type_ref":"builtins.dict"}}},"__doc__":{".class":"SymbolTableNode","kind":"Gdef","node":{".class":"Var","flags":["is_ready"],"fullname":"conda.history.__doc__","name":"__doc__","type":"builtins.str"}},"__file__":{".class":"SymbolTableNode","kind":"Gdef","node":{".class":"Var","flags":["is_ready"],"fullname":"conda.history.__file__","name":"__file__","type":"builtins.str"}},"__name__":{".class":"SymbolTableNode","kind":"Gdef","node":{".class":"Var","flags":["is_ready"],"fullname":"conda.history.__name__","name":"__name__","type":"builtins.str"}},"__package__":{".class":"SymbolTableNode","kind":"Gdef","node":{".class":"Var","flags":["is_ready"],"fullname":"conda.history.__package__","name":"__package__","type":"builtins.str"}},"__spec__":{".class":"SymbolTableNode","kind":"Gdef","node":{".class":"Var","flags":["is_ready"],"fullname":"conda.history.__spec__","name":"__spec__","type":"_frozen_importlib.ModuleSpec"}},"annotations":{".class":"SymbolTableNode","cross_ref":"__future__.annotations","kind":"Gdef"},"codecs":{".class":"SymbolTableNode","cross_ref":"codecs","kind":"Gdef"},"context":{".class":"SymbolTableNode","cross_ref":"conda.base.context.context","kind":"Gdef"},"dals":{".class":"SymbolTableNode","cross_ref":"conda.auxlib.ish.dals","kind":"Gdef"},"dedent":{".class":"SymbolTableNode","cross_ref":"textwrap.dedent","kind":"Gdef"},"dist_str_to_quad":{".class":"SymbolTableNode","cross_ref":"conda.models.dist.dist_str_to_quad","kind":"Gdef"},"ensure_text_type":{".class":"SymbolTableNode","cross_ref":"conda.common.compat.ensure_text_type","kind":"Gdef"},"groupby":{".class":"SymbolTableNode","cross_ref":"conda.common.iterators.groupby_to_dict","kind":"Gdef"},"h":{".class":"SymbolTableNode","kind":"Gdef","node":{".class":"Var","flags":["is_inferred","has_explicit_value"],"fullname":"conda.history.h","name":"h","type":"conda.history.History"}},"is_diff":{".class":"SymbolTableNode","kind":"Gdef","node":{".class":"FuncDef","abstract_status":0,"arg_kinds":[0],"arg_names":["content"],"dataclass_transform_spec":null,"deprecated":null,"flags":[],"fullname":"conda.history.is_diff","name":"is_diff","type":null}},"isdir":{".class":"SymbolTableNode","cross_ref":"genericpath.isdir","kind":"Gdef"},"isfile":{".class":"SymbolTableNode","cross_ref":"genericpath.isfile","kind":"Gdef"},"islice":{".class":"SymbolTableNode","cross_ref":"itertools.islice","kind":"Gdef"},"itemgetter":{".class":"SymbolTableNode","cross_ref":"operator.itemgetter","kind":"Gdef"},"join":{".class":"SymbolTableNode","cross_ref":"ntpath.join","kind":"Gdef"},"literal_eval":{".class":"SymbolTableNode","cross_ref":"ast.literal_eval","kind":"Gdef"},"log":{".class":"SymbolTableNode","kind":"Gdef","node":{".class":"Var","flags":["is_inferred","has_explicit_value"],"fullname":"conda.history.log","name":"log","type":"logging.Logger"}},"logging":{".class":"SymbolTableNode","cross_ref":"logging","kind":"Gdef"},"open_utf8":{".class":"SymbolTableNode","cross_ref":"conda.common.compat.open_utf8","kind":"Gdef"},"os":{".class":"SymbolTableNode","cross_ref":"os","kind":"Gdef"},"paths_equal":{".class":"SymbolTableNode","cross_ref":"conda.common.path.paths_equal","kind":"Gdef"},"pprint":{".class":"SymbolTableNode","cross_ref":"pprint.pprint","kind":"Gdef"},"pretty_content":{".class":"SymbolTableNode","kind":"Gdef","node":{".class":"FuncDef","abstract_status":0,"arg_kinds":[0],"arg_names":["content"],"dataclass_transform_spec":null,"deprecated":null,"flags":[],"fullname":"conda.history.pretty_content","name":"pretty_content","type":null}},"pretty_diff":{".class":"SymbolTableNode","kind":"Gdef","node":{".class":"FuncDef","abstract_status":0,"arg_kinds":[0],"arg_names":["diff"],"dataclass_transform_spec":null,"deprecated":null,"flags":[],"fullname":"conda.history.pretty_diff","name":"pretty_diff","type":null}},"re":{".class":"SymbolTableNode","cross_ref":"re","kind":"Gdef"},"sys":{".class":"SymbolTableNode","cross_ref":"sys","kind":"Gdef"},"time":{".class":"SymbolTableNode","cross_ref":"time","kind":"Gdef"},"touch":{".class":"SymbolTableNode","cross_ref":"conda.gateways.disk.update.touch","kind":"Gdef"},"version_relation_re":{".class":"SymbolTableNode","cross_ref":"conda.models.version.version_relation_re","kind":"Gdef"},"warnings":{".class":"SymbolTableNode","cross_ref":"warnings","kind":"Gdef"},"write_head":{".class":"SymbolTableNode","kind":"Gdef","node":{".class":"FuncDef","abstract_status":0,"arg_kinds":[0],"arg_names":["fo"],"dataclass_transform_spec":null,"deprecated":null,"flags":[],"fullname":"conda.history.write_head","name":"write_head","type":null}}},"path":"C:\\ProgramData\\anaconda3\\Lib\\site-packages\\conda\\history.py"}